{"nodes": [{"id": "c_t309_detectors_avh_align_av_hubert_fairseq_old_fairseq_logging_progress_bar_py", "label": "progress_bar.py", "file_type": "code", "source_file": "C:\\t309\\detectors\\AVH-Align\\av_hubert\\fairseq-old\\fairseq\\logging\\progress_bar.py", "source_location": "L1"}, {"id": "logging_progress_bar_progress_bar", "label": "progress_bar()", "file_type": "code", "source_file": "C:\\t309\\detectors\\AVH-Align\\av_hubert\\fairseq-old\\fairseq\\logging\\progress_bar.py", "source_location": "L28"}, {"id": "logging_progress_bar_build_progress_bar", "label": "build_progress_bar()", "file_type": "code", "source_file": "C:\\t309\\detectors\\AVH-Align\\av_hubert\\fairseq-old\\fairseq\\logging\\progress_bar.py", "source_location": "L80"}, {"id": "logging_progress_bar_format_stat", "label": "format_stat()", "file_type": "code", "source_file": "C:\\t309\\detectors\\AVH-Align\\av_hubert\\fairseq-old\\fairseq\\logging\\progress_bar.py", "source_location": "L106"}, {"id": "logging_progress_bar_baseprogressbar", "label": "BaseProgressBar", "file_type": "code", "source_file": "C:\\t309\\detectors\\AVH-Align\\av_hubert\\fairseq-old\\fairseq\\logging\\progress_bar.py", "source_location": "L120"}, {"id": "object", "label": "object", "file_type": "code", "source_file": "", "source_location": ""}, {"id": "logging_progress_bar_baseprogressbar_init", "label": ".__init__()", "file_type": "code", "source_file": "C:\\t309\\detectors\\AVH-Align\\av_hubert\\fairseq-old\\fairseq\\logging\\progress_bar.py", "source_location": "L123"}, {"id": "logging_progress_bar_baseprogressbar_len", "label": ".__len__()", "file_type": "code", "source_file": "C:\\t309\\detectors\\AVH-Align\\av_hubert\\fairseq-old\\fairseq\\logging\\progress_bar.py", "source_location": "L133"}, {"id": "logging_progress_bar_baseprogressbar_enter", "label": ".__enter__()", "file_type": "code", "source_file": "C:\\t309\\detectors\\AVH-Align\\av_hubert\\fairseq-old\\fairseq\\logging\\progress_bar.py", "source_location": "L136"}, {"id": "logging_progress_bar_baseprogressbar_exit", "label": ".__exit__()", "file_type": "code", "source_file": "C:\\t309\\detectors\\AVH-Align\\av_hubert\\fairseq-old\\fairseq\\logging\\progress_bar.py", "source_location": "L139"}, {"id": "logging_progress_bar_baseprogressbar_iter", "label": ".__iter__()", "file_type": "code", "source_file": "C:\\t309\\detectors\\AVH-Align\\av_hubert\\fairseq-old\\fairseq\\logging\\progress_bar.py", "source_location": "L142"}, {"id": "logging_progress_bar_baseprogressbar_log", "label": ".log()", "file_type": "code", "source_file": "C:\\t309\\detectors\\AVH-Align\\av_hubert\\fairseq-old\\fairseq\\logging\\progress_bar.py", "source_location": "L145"}, {"id": "logging_progress_bar_baseprogressbar_print", "label": ".print()", "file_type": "code", "source_file": "C:\\t309\\detectors\\AVH-Align\\av_hubert\\fairseq-old\\fairseq\\logging\\progress_bar.py", "source_location": "L149"}, {"id": "logging_progress_bar_baseprogressbar_update_config", "label": ".update_config()", "file_type": "code", "source_file": "C:\\t309\\detectors\\AVH-Align\\av_hubert\\fairseq-old\\fairseq\\logging\\progress_bar.py", "source_location": "L153"}, {"id": "logging_progress_bar_baseprogressbar_str_commas", "label": "._str_commas()", "file_type": "code", "source_file": "C:\\t309\\detectors\\AVH-Align\\av_hubert\\fairseq-old\\fairseq\\logging\\progress_bar.py", "source_location": "L157"}, {"id": "logging_progress_bar_baseprogressbar_str_pipes", "label": "._str_pipes()", "file_type": "code", "source_file": "C:\\t309\\detectors\\AVH-Align\\av_hubert\\fairseq-old\\fairseq\\logging\\progress_bar.py", "source_location": "L160"}, {"id": "logging_progress_bar_baseprogressbar_format_stats", "label": "._format_stats()", "file_type": "code", "source_file": "C:\\t309\\detectors\\AVH-Align\\av_hubert\\fairseq-old\\fairseq\\logging\\progress_bar.py", "source_location": "L163"}, {"id": "logging_progress_bar_rename_logger", "label": "rename_logger()", "file_type": "code", "source_file": "C:\\t309\\detectors\\AVH-Align\\av_hubert\\fairseq-old\\fairseq\\logging\\progress_bar.py", "source_location": "L172"}, {"id": "logging_progress_bar_jsonprogressbar", "label": "JsonProgressBar", "file_type": "code", "source_file": "C:\\t309\\detectors\\AVH-Align\\av_hubert\\fairseq-old\\fairseq\\logging\\progress_bar.py", "source_location": "L180"}, {"id": "logging_progress_bar_jsonprogressbar_init", "label": ".__init__()", "file_type": "code", "source_file": "C:\\t309\\detectors\\AVH-Align\\av_hubert\\fairseq-old\\fairseq\\logging\\progress_bar.py", "source_location": "L183"}, {"id": "logging_progress_bar_jsonprogressbar_iter", "label": ".__iter__()", "file_type": "code", "source_file": "C:\\t309\\detectors\\AVH-Align\\av_hubert\\fairseq-old\\fairseq\\logging\\progress_bar.py", "source_location": "L189"}, {"id": "logging_progress_bar_jsonprogressbar_log", "label": ".log()", "file_type": "code", "source_file": "C:\\t309\\detectors\\AVH-Align\\av_hubert\\fairseq-old\\fairseq\\logging\\progress_bar.py", "source_location": "L195"}, {"id": "logging_progress_bar_jsonprogressbar_print", "label": ".print()", "file_type": "code", "source_file": "C:\\t309\\detectors\\AVH-Align\\av_hubert\\fairseq-old\\fairseq\\logging\\progress_bar.py", "source_location": "L208"}, {"id": "logging_progress_bar_jsonprogressbar_format_stats", "label": "._format_stats()", "file_type": "code", "source_file": "C:\\t309\\detectors\\AVH-Align\\av_hubert\\fairseq-old\\fairseq\\logging\\progress_bar.py", "source_location": "L219"}, {"id": "logging_progress_bar_noopprogressbar", "label": "NoopProgressBar", "file_type": "code", "source_file": "C:\\t309\\detectors\\AVH-Align\\av_hubert\\fairseq-old\\fairseq\\logging\\progress_bar.py", "source_location": "L231"}, {"id": "logging_progress_bar_noopprogressbar_init", "label": ".__init__()", "file_type": "code", "source_file": "C:\\t309\\detectors\\AVH-Align\\av_hubert\\fairseq-old\\fairseq\\logging\\progress_bar.py", "source_location": "L234"}, {"id": "logging_progress_bar_noopprogressbar_iter", "label": ".__iter__()", "file_type": "code", "source_file": "C:\\t309\\detectors\\AVH-Align\\av_hubert\\fairseq-old\\fairseq\\logging\\progress_bar.py", "source_location": "L237"}, {"id": "logging_progress_bar_noopprogressbar_log", "label": ".log()", "file_type": "code", "source_file": "C:\\t309\\detectors\\AVH-Align\\av_hubert\\fairseq-old\\fairseq\\logging\\progress_bar.py", "source_location": "L241"}, {"id": "logging_progress_bar_noopprogressbar_print", "label": ".print()", "file_type": "code", "source_file": "C:\\t309\\detectors\\AVH-Align\\av_hubert\\fairseq-old\\fairseq\\logging\\progress_bar.py", "source_location": "L245"}, {"id": "logging_progress_bar_simpleprogressbar", "label": "SimpleProgressBar", "file_type": "code", "source_file": "C:\\t309\\detectors\\AVH-Align\\av_hubert\\fairseq-old\\fairseq\\logging\\progress_bar.py", "source_location": "L250"}, {"id": "logging_progress_bar_simpleprogressbar_init", "label": ".__init__()", "file_type": "code", "source_file": "C:\\t309\\detectors\\AVH-Align\\av_hubert\\fairseq-old\\fairseq\\logging\\progress_bar.py", "source_location": "L253"}, {"id": "logging_progress_bar_simpleprogressbar_iter", "label": ".__iter__()", "file_type": "code", "source_file": "C:\\t309\\detectors\\AVH-Align\\av_hubert\\fairseq-old\\fairseq\\logging\\progress_bar.py", "source_location": "L259"}, {"id": "logging_progress_bar_simpleprogressbar_log", "label": ".log()", "file_type": "code", "source_file": "C:\\t309\\detectors\\AVH-Align\\av_hubert\\fairseq-old\\fairseq\\logging\\progress_bar.py", "source_location": "L265"}, {"id": "logging_progress_bar_simpleprogressbar_print", "label": ".print()", "file_type": "code", "source_file": "C:\\t309\\detectors\\AVH-Align\\av_hubert\\fairseq-old\\fairseq\\logging\\progress_bar.py", "source_location": "L278"}, {"id": "logging_progress_bar_tqdmprogressbar", "label": "TqdmProgressBar", "file_type": "code", "source_file": "C:\\t309\\detectors\\AVH-Align\\av_hubert\\fairseq-old\\fairseq\\logging\\progress_bar.py", "source_location": "L285"}, {"id": "logging_progress_bar_tqdmprogressbar_init", "label": ".__init__()", "file_type": "code", "source_file": "C:\\t309\\detectors\\AVH-Align\\av_hubert\\fairseq-old\\fairseq\\logging\\progress_bar.py", "source_location": "L288"}, {"id": "logging_progress_bar_tqdmprogressbar_iter", "label": ".__iter__()", "file_type": "code", "source_file": "C:\\t309\\detectors\\AVH-Align\\av_hubert\\fairseq-old\\fairseq\\logging\\progress_bar.py", "source_location": "L299"}, {"id": "logging_progress_bar_tqdmprogressbar_log", "label": ".log()", "file_type": "code", "source_file": "C:\\t309\\detectors\\AVH-Align\\av_hubert\\fairseq-old\\fairseq\\logging\\progress_bar.py", "source_location": "L302"}, {"id": "logging_progress_bar_tqdmprogressbar_print", "label": ".print()", "file_type": "code", "source_file": "C:\\t309\\detectors\\AVH-Align\\av_hubert\\fairseq-old\\fairseq\\logging\\progress_bar.py", "source_location": "L306"}, {"id": "logging_progress_bar_close_writers", "label": "_close_writers()", "file_type": "code", "source_file": "C:\\t309\\detectors\\AVH-Align\\av_hubert\\fairseq-old\\fairseq\\logging\\progress_bar.py", "source_location": "L323"}, {"id": "logging_progress_bar_tensorboardprogressbarwrapper", "label": "TensorboardProgressBarWrapper", "file_type": "code", "source_file": "C:\\t309\\detectors\\AVH-Align\\av_hubert\\fairseq-old\\fairseq\\logging\\progress_bar.py", "source_location": "L331"}, {"id": "logging_progress_bar_tensorboardprogressbarwrapper_init", "label": ".__init__()", "file_type": "code", "source_file": "C:\\t309\\detectors\\AVH-Align\\av_hubert\\fairseq-old\\fairseq\\logging\\progress_bar.py", "source_location": "L334"}, {"id": "logging_progress_bar_tensorboardprogressbarwrapper_writer", "label": "._writer()", "file_type": "code", "source_file": "C:\\t309\\detectors\\AVH-Align\\av_hubert\\fairseq-old\\fairseq\\logging\\progress_bar.py", "source_location": "L343"}, {"id": "logging_progress_bar_tensorboardprogressbarwrapper_iter", "label": ".__iter__()", "file_type": "code", "source_file": "C:\\t309\\detectors\\AVH-Align\\av_hubert\\fairseq-old\\fairseq\\logging\\progress_bar.py", "source_location": "L352"}, {"id": "logging_progress_bar_tensorboardprogressbarwrapper_log", "label": ".log()", "file_type": "code", "source_file": "C:\\t309\\detectors\\AVH-Align\\av_hubert\\fairseq-old\\fairseq\\logging\\progress_bar.py", "source_location": "L355"}, {"id": "logging_progress_bar_tensorboardprogressbarwrapper_print", "label": ".print()", "file_type": "code", "source_file": "C:\\t309\\detectors\\AVH-Align\\av_hubert\\fairseq-old\\fairseq\\logging\\progress_bar.py", "source_location": "L360"}, {"id": "logging_progress_bar_tensorboardprogressbarwrapper_update_config", "label": ".update_config()", "file_type": "code", "source_file": "C:\\t309\\detectors\\AVH-Align\\av_hubert\\fairseq-old\\fairseq\\logging\\progress_bar.py", "source_location": "L365"}, {"id": "logging_progress_bar_tensorboardprogressbarwrapper_log_to_tensorboard", "label": "._log_to_tensorboard()", "file_type": "code", "source_file": "C:\\t309\\detectors\\AVH-Align\\av_hubert\\fairseq-old\\fairseq\\logging\\progress_bar.py", "source_location": "L370"}, {"id": "logging_progress_bar_wandbprogressbarwrapper", "label": "WandBProgressBarWrapper", "file_type": "code", "source_file": "C:\\t309\\detectors\\AVH-Align\\av_hubert\\fairseq-old\\fairseq\\logging\\progress_bar.py", "source_location": "L392"}, {"id": "logging_progress_bar_wandbprogressbarwrapper_init", "label": ".__init__()", "file_type": "code", "source_file": "C:\\t309\\detectors\\AVH-Align\\av_hubert\\fairseq-old\\fairseq\\logging\\progress_bar.py", "source_location": "L395"}, {"id": "logging_progress_bar_wandbprogressbarwrapper_iter", "label": ".__iter__()", "file_type": "code", "source_file": "C:\\t309\\detectors\\AVH-Align\\av_hubert\\fairseq-old\\fairseq\\logging\\progress_bar.py", "source_location": "L405"}, {"id": "logging_progress_bar_wandbprogressbarwrapper_log", "label": ".log()", "file_type": "code", "source_file": "C:\\t309\\detectors\\AVH-Align\\av_hubert\\fairseq-old\\fairseq\\logging\\progress_bar.py", "source_location": "L408"}, {"id": "logging_progress_bar_wandbprogressbarwrapper_print", "label": ".print()", "file_type": "code", "source_file": "C:\\t309\\detectors\\AVH-Align\\av_hubert\\fairseq-old\\fairseq\\logging\\progress_bar.py", "source_location": "L413"}, {"id": "logging_progress_bar_wandbprogressbarwrapper_update_config", "label": ".update_config()", "file_type": "code", "source_file": "C:\\t309\\detectors\\AVH-Align\\av_hubert\\fairseq-old\\fairseq\\logging\\progress_bar.py", "source_location": "L418"}, {"id": "logging_progress_bar_wandbprogressbarwrapper_log_to_wandb", "label": "._log_to_wandb()", "file_type": "code", "source_file": "C:\\t309\\detectors\\AVH-Align\\av_hubert\\fairseq-old\\fairseq\\logging\\progress_bar.py", "source_location": "L424"}, {"id": "logging_progress_bar_azuremlprogressbarwrapper", "label": "AzureMLProgressBarWrapper", "file_type": "code", "source_file": "C:\\t309\\detectors\\AVH-Align\\av_hubert\\fairseq-old\\fairseq\\logging\\progress_bar.py", "source_location": "L445"}, {"id": "logging_progress_bar_azuremlprogressbarwrapper_init", "label": ".__init__()", "file_type": "code", "source_file": "C:\\t309\\detectors\\AVH-Align\\av_hubert\\fairseq-old\\fairseq\\logging\\progress_bar.py", "source_location": "L448"}, {"id": "logging_progress_bar_azuremlprogressbarwrapper_exit", "label": ".__exit__()", "file_type": "code", "source_file": "C:\\t309\\detectors\\AVH-Align\\av_hubert\\fairseq-old\\fairseq\\logging\\progress_bar.py", "source_location": "L455"}, {"id": "logging_progress_bar_azuremlprogressbarwrapper_iter", "label": ".__iter__()", "file_type": "code", "source_file": "C:\\t309\\detectors\\AVH-Align\\av_hubert\\fairseq-old\\fairseq\\logging\\progress_bar.py", "source_location": "L460"}, {"id": "logging_progress_bar_azuremlprogressbarwrapper_log", "label": ".log()", "file_type": "code", "source_file": "C:\\t309\\detectors\\AVH-Align\\av_hubert\\fairseq-old\\fairseq\\logging\\progress_bar.py", "source_location": "L463"}, {"id": "logging_progress_bar_azuremlprogressbarwrapper_print", "label": ".print()", "file_type": "code", "source_file": "C:\\t309\\detectors\\AVH-Align\\av_hubert\\fairseq-old\\fairseq\\logging\\progress_bar.py", "source_location": "L468"}, {"id": "logging_progress_bar_azuremlprogressbarwrapper_update_config", "label": ".update_config()", "file_type": "code", "source_file": "C:\\t309\\detectors\\AVH-Align\\av_hubert\\fairseq-old\\fairseq\\logging\\progress_bar.py", "source_location": "L473"}, {"id": "logging_progress_bar_azuremlprogressbarwrapper_log_to_azureml", "label": "._log_to_azureml()", "file_type": "code", "source_file": "C:\\t309\\detectors\\AVH-Align\\av_hubert\\fairseq-old\\fairseq\\logging\\progress_bar.py", "source_location": "L477"}, {"id": "logging_progress_bar_rationale_88", "label": "Legacy wrapper that takes an argparse.Namespace.", "file_type": "rationale", "source_file": "C:\\t309\\detectors\\AVH-Align\\av_hubert\\fairseq-old\\fairseq\\logging\\progress_bar.py", "source_location": "L88"}, {"id": "logging_progress_bar_rationale_121", "label": "Abstract class for progress bars.", "file_type": "rationale", "source_file": "C:\\t309\\detectors\\AVH-Align\\av_hubert\\fairseq-old\\fairseq\\logging\\progress_bar.py", "source_location": "L121"}, {"id": "logging_progress_bar_rationale_146", "label": "Log intermediate stats according to log_interval.", "file_type": "rationale", "source_file": "C:\\t309\\detectors\\AVH-Align\\av_hubert\\fairseq-old\\fairseq\\logging\\progress_bar.py", "source_location": "L146"}, {"id": "logging_progress_bar_rationale_150", "label": "Print end-of-epoch stats.", "file_type": "rationale", "source_file": "C:\\t309\\detectors\\AVH-Align\\av_hubert\\fairseq-old\\fairseq\\logging\\progress_bar.py", "source_location": "L150"}, {"id": "logging_progress_bar_rationale_154", "label": "Log latest configuration.", "file_type": "rationale", "source_file": "C:\\t309\\detectors\\AVH-Align\\av_hubert\\fairseq-old\\fairseq\\logging\\progress_bar.py", "source_location": "L154"}, {"id": "logging_progress_bar_rationale_181", "label": "Log output in JSON format.", "file_type": "rationale", "source_file": "C:\\t309\\detectors\\AVH-Align\\av_hubert\\fairseq-old\\fairseq\\logging\\progress_bar.py", "source_location": "L181"}, {"id": "logging_progress_bar_rationale_196", "label": "Log intermediate stats according to log_interval.", "file_type": "rationale", "source_file": "C:\\t309\\detectors\\AVH-Align\\av_hubert\\fairseq-old\\fairseq\\logging\\progress_bar.py", "source_location": "L196"}, {"id": "logging_progress_bar_rationale_209", "label": "Print end-of-epoch stats.", "file_type": "rationale", "source_file": "C:\\t309\\detectors\\AVH-Align\\av_hubert\\fairseq-old\\fairseq\\logging\\progress_bar.py", "source_location": "L209"}, {"id": "logging_progress_bar_rationale_242", "label": "Log intermediate stats according to log_interval.", "file_type": "rationale", "source_file": "C:\\t309\\detectors\\AVH-Align\\av_hubert\\fairseq-old\\fairseq\\logging\\progress_bar.py", "source_location": "L242"}, {"id": "logging_progress_bar_rationale_246", "label": "Print end-of-epoch stats.", "file_type": "rationale", "source_file": "C:\\t309\\detectors\\AVH-Align\\av_hubert\\fairseq-old\\fairseq\\logging\\progress_bar.py", "source_location": "L246"}, {"id": "logging_progress_bar_rationale_251", "label": "A minimal logger for non-TTY environments.", "file_type": "rationale", "source_file": "C:\\t309\\detectors\\AVH-Align\\av_hubert\\fairseq-old\\fairseq\\logging\\progress_bar.py", "source_location": "L251"}, {"id": "logging_progress_bar_rationale_266", "label": "Log intermediate stats according to log_interval.", "file_type": "rationale", "source_file": "C:\\t309\\detectors\\AVH-Align\\av_hubert\\fairseq-old\\fairseq\\logging\\progress_bar.py", "source_location": "L266"}, {"id": "logging_progress_bar_rationale_279", "label": "Print end-of-epoch stats.", "file_type": "rationale", "source_file": "C:\\t309\\detectors\\AVH-Align\\av_hubert\\fairseq-old\\fairseq\\logging\\progress_bar.py", "source_location": "L279"}, {"id": "logging_progress_bar_rationale_303", "label": "Log intermediate stats according to log_interval.", "file_type": "rationale", "source_file": "C:\\t309\\detectors\\AVH-Align\\av_hubert\\fairseq-old\\fairseq\\logging\\progress_bar.py", "source_location": "L303"}, {"id": "logging_progress_bar_rationale_307", "label": "Print end-of-epoch stats.", "file_type": "rationale", "source_file": "C:\\t309\\detectors\\AVH-Align\\av_hubert\\fairseq-old\\fairseq\\logging\\progress_bar.py", "source_location": "L307"}, {"id": "logging_progress_bar_rationale_356", "label": "Log intermediate stats to tensorboard.", "file_type": "rationale", "source_file": "C:\\t309\\detectors\\AVH-Align\\av_hubert\\fairseq-old\\fairseq\\logging\\progress_bar.py", "source_location": "L356"}, {"id": "logging_progress_bar_rationale_361", "label": "Print end-of-epoch stats.", "file_type": "rationale", "source_file": "C:\\t309\\detectors\\AVH-Align\\av_hubert\\fairseq-old\\fairseq\\logging\\progress_bar.py", "source_location": "L361"}, {"id": "logging_progress_bar_rationale_366", "label": "Log latest configuration.", "file_type": "rationale", "source_file": "C:\\t309\\detectors\\AVH-Align\\av_hubert\\fairseq-old\\fairseq\\logging\\progress_bar.py", "source_location": "L366"}, {"id": "logging_progress_bar_rationale_393", "label": "Log to Weights & Biases.", "file_type": "rationale", "source_file": "C:\\t309\\detectors\\AVH-Align\\av_hubert\\fairseq-old\\fairseq\\logging\\progress_bar.py", "source_location": "L393"}, {"id": "logging_progress_bar_rationale_409", "label": "Log intermediate stats to tensorboard.", "file_type": "rationale", "source_file": "C:\\t309\\detectors\\AVH-Align\\av_hubert\\fairseq-old\\fairseq\\logging\\progress_bar.py", "source_location": "L409"}, {"id": "logging_progress_bar_rationale_414", "label": "Print end-of-epoch stats.", "file_type": "rationale", "source_file": "C:\\t309\\detectors\\AVH-Align\\av_hubert\\fairseq-old\\fairseq\\logging\\progress_bar.py", "source_location": "L414"}, {"id": "logging_progress_bar_rationale_419", "label": "Log latest configuration.", "file_type": "rationale", "source_file": "C:\\t309\\detectors\\AVH-Align\\av_hubert\\fairseq-old\\fairseq\\logging\\progress_bar.py", "source_location": "L419"}, {"id": "logging_progress_bar_rationale_464", "label": "Log intermediate stats to AzureML", "file_type": "rationale", "source_file": "C:\\t309\\detectors\\AVH-Align\\av_hubert\\fairseq-old\\fairseq\\logging\\progress_bar.py", "source_location": "L464"}, {"id": "logging_progress_bar_rationale_469", "label": "Print end-of-epoch stats", "file_type": "rationale", "source_file": "C:\\t309\\detectors\\AVH-Align\\av_hubert\\fairseq-old\\fairseq\\logging\\progress_bar.py", "source_location": "L469"}, {"id": "logging_progress_bar_rationale_474", "label": "Log latest configuration.", "file_type": "rationale", "source_file": "C:\\t309\\detectors\\AVH-Align\\av_hubert\\fairseq-old\\fairseq\\logging\\progress_bar.py", "source_location": "L474"}], "edges": [{"source": "c_t309_detectors_avh_align_av_hubert_fairseq_old_fairseq_logging_progress_bar_py", "target": "atexit", "relation": "imports", "context": "import", "confidence": "EXTRACTED", "source_file": "C:\\t309\\detectors\\AVH-Align\\av_hubert\\fairseq-old\\fairseq\\logging\\progress_bar.py", "source_location": "L10", "weight": 1.0}, {"source": "c_t309_detectors_avh_align_av_hubert_fairseq_old_fairseq_logging_progress_bar_py", "target": "json", "relation": "imports", "context": "import", "confidence": "EXTRACTED", "source_file": "C:\\t309\\detectors\\AVH-Align\\av_hubert\\fairseq-old\\fairseq\\logging\\progress_bar.py", "source_location": "L11", "weight": 1.0}, {"source": "c_t309_detectors_avh_align_av_hubert_fairseq_old_fairseq_logging_progress_bar_py", "target": "logging", "relation": "imports", "context": "import", "confidence": "EXTRACTED", "source_file": "C:\\t309\\detectors\\AVH-Align\\av_hubert\\fairseq-old\\fairseq\\logging\\progress_bar.py", "source_location": "L12", "weight": 1.0}, {"source": "c_t309_detectors_avh_align_av_hubert_fairseq_old_fairseq_logging_progress_bar_py", "target": "os", "relation": "imports", "context": "import", "confidence": "EXTRACTED", "source_file": "C:\\t309\\detectors\\AVH-Align\\av_hubert\\fairseq-old\\fairseq\\logging\\progress_bar.py", "source_location": "L13", "weight": 1.0}, {"source": "c_t309_detectors_avh_align_av_hubert_fairseq_old_fairseq_logging_progress_bar_py", "target": "sys", "relation": "imports", "context": "import", "confidence": "EXTRACTED", "source_file": "C:\\t309\\detectors\\AVH-Align\\av_hubert\\fairseq-old\\fairseq\\logging\\progress_bar.py", "source_location": "L14", "weight": 1.0}, {"source": "c_t309_detectors_avh_align_av_hubert_fairseq_old_fairseq_logging_progress_bar_py", "target": "collections", "relation": "imports_from", "context": "import", "confidence": "EXTRACTED", "source_file": "C:\\t309\\detectors\\AVH-Align\\av_hubert\\fairseq-old\\fairseq\\logging\\progress_bar.py", "source_location": "L15", "weight": 1.0}, {"source": "c_t309_detectors_avh_align_av_hubert_fairseq_old_fairseq_logging_progress_bar_py", "target": "contextlib", "relation": "imports_from", "context": "import", "confidence": "EXTRACTED", "source_file": "C:\\t309\\detectors\\AVH-Align\\av_hubert\\fairseq-old\\fairseq\\logging\\progress_bar.py", "source_location": "L16", "weight": 1.0}, {"source": "c_t309_detectors_avh_align_av_hubert_fairseq_old_fairseq_logging_progress_bar_py", "target": "numbers", "relation": "imports_from", "context": "import", "confidence": "EXTRACTED", "source_file": "C:\\t309\\detectors\\AVH-Align\\av_hubert\\fairseq-old\\fairseq\\logging\\progress_bar.py", "source_location": "L17", "weight": 1.0}, {"source": "c_t309_detectors_avh_align_av_hubert_fairseq_old_fairseq_logging_progress_bar_py", "target": "typing", "relation": "imports_from", "context": "import", "confidence": "EXTRACTED", "source_file": "C:\\t309\\detectors\\AVH-Align\\av_hubert\\fairseq-old\\fairseq\\logging\\progress_bar.py", "source_location": "L18", "weight": 1.0}, {"source": "c_t309_detectors_avh_align_av_hubert_fairseq_old_fairseq_logging_progress_bar_py", "target": "torch", "relation": "imports", "context": "import", "confidence": "EXTRACTED", "source_file": "C:\\t309\\detectors\\AVH-Align\\av_hubert\\fairseq-old\\fairseq\\logging\\progress_bar.py", "source_location": "L20", "weight": 1.0}, {"source": "c_t309_detectors_avh_align_av_hubert_fairseq_old_fairseq_logging_progress_bar_py", "target": "c_t309_detectors_avh_align_av_hubert_fairseq_old_fairseq_logging_meters_py", "relation": "imports_from", "context": "import", "confidence": "EXTRACTED", "source_file": "C:\\t309\\detectors\\AVH-Align\\av_hubert\\fairseq-old\\fairseq\\logging\\progress_bar.py", "source_location": "L22", "weight": 1.0}, {"source": "c_t309_detectors_avh_align_av_hubert_fairseq_old_fairseq_logging_progress_bar_py", "target": "logging_progress_bar_progress_bar", "relation": "contains", "confidence": "EXTRACTED", "source_file": "C:\\t309\\detectors\\AVH-Align\\av_hubert\\fairseq-old\\fairseq\\logging\\progress_bar.py", "source_location": "L28", "weight": 1.0}, {"source": "c_t309_detectors_avh_align_av_hubert_fairseq_old_fairseq_logging_progress_bar_py", "target": "logging_progress_bar_build_progress_bar", "relation": "contains", "confidence": "EXTRACTED", "source_file": "C:\\t309\\detectors\\AVH-Align\\av_hubert\\fairseq-old\\fairseq\\logging\\progress_bar.py", "source_location": "L80", "weight": 1.0}, {"source": "c_t309_detectors_avh_align_av_hubert_fairseq_old_fairseq_logging_progress_bar_py", "target": "logging_progress_bar_format_stat", "relation": "contains", "confidence": "EXTRACTED", "source_file": "C:\\t309\\detectors\\AVH-Align\\av_hubert\\fairseq-old\\fairseq\\logging\\progress_bar.py", "source_location": "L106", "weight": 1.0}, {"source": "c_t309_detectors_avh_align_av_hubert_fairseq_old_fairseq_logging_progress_bar_py", "target": "logging_progress_bar_baseprogressbar", "relation": "contains", "confidence": "EXTRACTED", "source_file": "C:\\t309\\detectors\\AVH-Align\\av_hubert\\fairseq-old\\fairseq\\logging\\progress_bar.py", "source_location": "L120", "weight": 1.0}, {"source": "logging_progress_bar_baseprogressbar", "target": "object", "relation": "inherits", "confidence": "EXTRACTED", "source_file": "C:\\t309\\detectors\\AVH-Align\\av_hubert\\fairseq-old\\fairseq\\logging\\progress_bar.py", "source_location": "L120", "weight": 1.0}, {"source": "logging_progress_bar_baseprogressbar", "target": "logging_progress_bar_baseprogressbar_init", "relation": "method", "confidence": "EXTRACTED", "source_file": "C:\\t309\\detectors\\AVH-Align\\av_hubert\\fairseq-old\\fairseq\\logging\\progress_bar.py", "source_location": "L123", "weight": 1.0}, {"source": "logging_progress_bar_baseprogressbar", "target": "logging_progress_bar_baseprogressbar_len", "relation": "method", "confidence": "EXTRACTED", "source_file": "C:\\t309\\detectors\\AVH-Align\\av_hubert\\fairseq-old\\fairseq\\logging\\progress_bar.py", "source_location": "L133", "weight": 1.0}, {"source": "logging_progress_bar_baseprogressbar", "target": "logging_progress_bar_baseprogressbar_enter", "relation": "method", "confidence": "EXTRACTED", "source_file": "C:\\t309\\detectors\\AVH-Align\\av_hubert\\fairseq-old\\fairseq\\logging\\progress_bar.py", "source_location": "L136", "weight": 1.0}, {"source": "logging_progress_bar_baseprogressbar", "target": "logging_progress_bar_baseprogressbar_exit", "relation": "method", "confidence": "EXTRACTED", "source_file": "C:\\t309\\detectors\\AVH-Align\\av_hubert\\fairseq-old\\fairseq\\logging\\progress_bar.py", "source_location": "L139", "weight": 1.0}, {"source": "logging_progress_bar_baseprogressbar", "target": "logging_progress_bar_baseprogressbar_iter", "relation": "method", "confidence": "EXTRACTED", "source_file": "C:\\t309\\detectors\\AVH-Align\\av_hubert\\fairseq-old\\fairseq\\logging\\progress_bar.py", "source_location": "L142", "weight": 1.0}, {"source": "logging_progress_bar_baseprogressbar", "target": "logging_progress_bar_baseprogressbar_log", "relation": "method", "confidence": "EXTRACTED", "source_file": "C:\\t309\\detectors\\AVH-Align\\av_hubert\\fairseq-old\\fairseq\\logging\\progress_bar.py", "source_location": "L145", "weight": 1.0}, {"source": "logging_progress_bar_baseprogressbar", "target": "logging_progress_bar_baseprogressbar_print", "relation": "method", "confidence": "EXTRACTED", "source_file": "C:\\t309\\detectors\\AVH-Align\\av_hubert\\fairseq-old\\fairseq\\logging\\progress_bar.py", "source_location": "L149", "weight": 1.0}, {"source": "logging_progress_bar_baseprogressbar", "target": "logging_progress_bar_baseprogressbar_update_config", "relation": "method", "confidence": "EXTRACTED", "source_file": "C:\\t309\\detectors\\AVH-Align\\av_hubert\\fairseq-old\\fairseq\\logging\\progress_bar.py", "source_location": "L153", "weight": 1.0}, {"source": "logging_progress_bar_baseprogressbar", "target": "logging_progress_bar_baseprogressbar_str_commas", "relation": "method", "confidence": "EXTRACTED", "source_file": "C:\\t309\\detectors\\AVH-Align\\av_hubert\\fairseq-old\\fairseq\\logging\\progress_bar.py", "source_location": "L157", "weight": 1.0}, {"source": "logging_progress_bar_baseprogressbar", "target": "logging_progress_bar_baseprogressbar_str_pipes", "relation": "method", "confidence": "EXTRACTED", "source_file": "C:\\t309\\detectors\\AVH-Align\\av_hubert\\fairseq-old\\fairseq\\logging\\progress_bar.py", "source_location": "L160", "weight": 1.0}, {"source": "logging_progress_bar_baseprogressbar", "target": "logging_progress_bar_baseprogressbar_format_stats", "relation": "method", "confidence": "EXTRACTED", "source_file": "C:\\t309\\detectors\\AVH-Align\\av_hubert\\fairseq-old\\fairseq\\logging\\progress_bar.py", "source_location": "L163", "weight": 1.0}, {"source": "c_t309_detectors_avh_align_av_hubert_fairseq_old_fairseq_logging_progress_bar_py", "target": "logging_progress_bar_rename_logger", "relation": "contains", "confidence": "EXTRACTED", "source_file": "C:\\t309\\detectors\\AVH-Align\\av_hubert\\fairseq-old\\fairseq\\logging\\progress_bar.py", "source_location": "L172", "weight": 1.0}, {"source": "c_t309_detectors_avh_align_av_hubert_fairseq_old_fairseq_logging_progress_bar_py", "target": "logging_progress_bar_jsonprogressbar", "relation": "contains", "confidence": "EXTRACTED", "source_file": "C:\\t309\\detectors\\AVH-Align\\av_hubert\\fairseq-old\\fairseq\\logging\\progress_bar.py", "source_location": "L180", "weight": 1.0}, {"source": "logging_progress_bar_jsonprogressbar", "target": "logging_progress_bar_baseprogressbar", "relation": "inherits", "confidence": "EXTRACTED", "source_file": "C:\\t309\\detectors\\AVH-Align\\av_hubert\\fairseq-old\\fairseq\\logging\\progress_bar.py", "source_location": "L180", "weight": 1.0}, {"source": "logging_progress_bar_jsonprogressbar", "target": "logging_progress_bar_jsonprogressbar_init", "relation": "method", "confidence": "EXTRACTED", "source_file": "C:\\t309\\detectors\\AVH-Align\\av_hubert\\fairseq-old\\fairseq\\logging\\progress_bar.py", "source_location": "L183", "weight": 1.0}, {"source": "logging_progress_bar_jsonprogressbar", "target": "logging_progress_bar_jsonprogressbar_iter", "relation": "method", "confidence": "EXTRACTED", "source_file": "C:\\t309\\detectors\\AVH-Align\\av_hubert\\fairseq-old\\fairseq\\logging\\progress_bar.py", "source_location": "L189", "weight": 1.0}, {"source": "logging_progress_bar_jsonprogressbar", "target": "logging_progress_bar_jsonprogressbar_log", "relation": "method", "confidence": "EXTRACTED", "source_file": "C:\\t309\\detectors\\AVH-Align\\av_hubert\\fairseq-old\\fairseq\\logging\\progress_bar.py", "source_location": "L195", "weight": 1.0}, {"source": "logging_progress_bar_jsonprogressbar", "target": "logging_progress_bar_jsonprogressbar_print", "relation": "method", "confidence": "EXTRACTED", "source_file": "C:\\t309\\detectors\\AVH-Align\\av_hubert\\fairseq-old\\fairseq\\logging\\progress_bar.py", "source_location": "L208", "weight": 1.0}, {"source": "logging_progress_bar_jsonprogressbar", "target": "logging_progress_bar_jsonprogressbar_format_stats", "relation": "method", "confidence": "EXTRACTED", "source_file": "C:\\t309\\detectors\\AVH-Align\\av_hubert\\fairseq-old\\fairseq\\logging\\progress_bar.py", "source_location": "L219", "weight": 1.0}, {"source": "c_t309_detectors_avh_align_av_hubert_fairseq_old_fairseq_logging_progress_bar_py", "target": "logging_progress_bar_noopprogressbar", "relation": "contains", "confidence": "EXTRACTED", "source_file": "C:\\t309\\detectors\\AVH-Align\\av_hubert\\fairseq-old\\fairseq\\logging\\progress_bar.py", "source_location": "L231", "weight": 1.0}, {"source": "logging_progress_bar_noopprogressbar", "target": "logging_progress_bar_baseprogressbar", "relation": "inherits", "confidence": "EXTRACTED", "source_file": "C:\\t309\\detectors\\AVH-Align\\av_hubert\\fairseq-old\\fairseq\\logging\\progress_bar.py", "source_location": "L231", "weight": 1.0}, {"source": "logging_progress_bar_noopprogressbar", "target": "logging_progress_bar_noopprogressbar_init", "relation": "method", "confidence": "EXTRACTED", "source_file": "C:\\t309\\detectors\\AVH-Align\\av_hubert\\fairseq-old\\fairseq\\logging\\progress_bar.py", "source_location": "L234", "weight": 1.0}, {"source": "logging_progress_bar_noopprogressbar", "target": "logging_progress_bar_noopprogressbar_iter", "relation": "method", "confidence": "EXTRACTED", "source_file": "C:\\t309\\detectors\\AVH-Align\\av_hubert\\fairseq-old\\fairseq\\logging\\progress_bar.py", "source_location": "L237", "weight": 1.0}, {"source": "logging_progress_bar_noopprogressbar", "target": "logging_progress_bar_noopprogressbar_log", "relation": "method", "confidence": "EXTRACTED", "source_file": "C:\\t309\\detectors\\AVH-Align\\av_hubert\\fairseq-old\\fairseq\\logging\\progress_bar.py", "source_location": "L241", "weight": 1.0}, {"source": "logging_progress_bar_noopprogressbar", "target": "logging_progress_bar_noopprogressbar_print", "relation": "method", "confidence": "EXTRACTED", "source_file": "C:\\t309\\detectors\\AVH-Align\\av_hubert\\fairseq-old\\fairseq\\logging\\progress_bar.py", "source_location": "L245", "weight": 1.0}, {"source": "c_t309_detectors_avh_align_av_hubert_fairseq_old_fairseq_logging_progress_bar_py", "target": "logging_progress_bar_simpleprogressbar", "relation": "contains", "confidence": "EXTRACTED", "source_file": "C:\\t309\\detectors\\AVH-Align\\av_hubert\\fairseq-old\\fairseq\\logging\\progress_bar.py", "source_location": "L250", "weight": 1.0}, {"source": "logging_progress_bar_simpleprogressbar", "target": "logging_progress_bar_baseprogressbar", "relation": "inherits", "confidence": "EXTRACTED", "source_file": "C:\\t309\\detectors\\AVH-Align\\av_hubert\\fairseq-old\\fairseq\\logging\\progress_bar.py", "source_location": "L250", "weight": 1.0}, {"source": "logging_progress_bar_simpleprogressbar", "target": "logging_progress_bar_simpleprogressbar_init", "relation": "method", "confidence": "EXTRACTED", "source_file": "C:\\t309\\detectors\\AVH-Align\\av_hubert\\fairseq-old\\fairseq\\logging\\progress_bar.py", "source_location": "L253", "weight": 1.0}, {"source": "logging_progress_bar_simpleprogressbar", "target": "logging_progress_bar_simpleprogressbar_iter", "relation": "method", "confidence": "EXTRACTED", "source_file": "C:\\t309\\detectors\\AVH-Align\\av_hubert\\fairseq-old\\fairseq\\logging\\progress_bar.py", "source_location": "L259", "weight": 1.0}, {"source": "logging_progress_bar_simpleprogressbar", "target": "logging_progress_bar_simpleprogressbar_log", "relation": "method", "confidence": "EXTRACTED", "source_file": "C:\\t309\\detectors\\AVH-Align\\av_hubert\\fairseq-old\\fairseq\\logging\\progress_bar.py", "source_location": "L265", "weight": 1.0}, {"source": "logging_progress_bar_simpleprogressbar", "target": "logging_progress_bar_simpleprogressbar_print", "relation": "method", "confidence": "EXTRACTED", "source_file": "C:\\t309\\detectors\\AVH-Align\\av_hubert\\fairseq-old\\fairseq\\logging\\progress_bar.py", "source_location": "L278", "weight": 1.0}, {"source": "c_t309_detectors_avh_align_av_hubert_fairseq_old_fairseq_logging_progress_bar_py", "target": "logging_progress_bar_tqdmprogressbar", "relation": "contains", "confidence": "EXTRACTED", "source_file": "C:\\t309\\detectors\\AVH-Align\\av_hubert\\fairseq-old\\fairseq\\logging\\progress_bar.py", "source_location": "L285", "weight": 1.0}, {"source": "logging_progress_bar_tqdmprogressbar", "target": "logging_progress_bar_baseprogressbar", "relation": "inherits", "confidence": "EXTRACTED", "source_file": "C:\\t309\\detectors\\AVH-Align\\av_hubert\\fairseq-old\\fairseq\\logging\\progress_bar.py", "source_location": "L285", "weight": 1.0}, {"source": "logging_progress_bar_tqdmprogressbar", "target": "logging_progress_bar_tqdmprogressbar_init", "relation": "method", "confidence": "EXTRACTED", "source_file": "C:\\t309\\detectors\\AVH-Align\\av_hubert\\fairseq-old\\fairseq\\logging\\progress_bar.py", "source_location": "L288", "weight": 1.0}, {"source": "logging_progress_bar_tqdmprogressbar", "target": "logging_progress_bar_tqdmprogressbar_iter", "relation": "method", "confidence": "EXTRACTED", "source_file": "C:\\t309\\detectors\\AVH-Align\\av_hubert\\fairseq-old\\fairseq\\logging\\progress_bar.py", "source_location": "L299", "weight": 1.0}, {"source": "logging_progress_bar_tqdmprogressbar", "target": "logging_progress_bar_tqdmprogressbar_log", "relation": "method", "confidence": "EXTRACTED", "source_file": "C:\\t309\\detectors\\AVH-Align\\av_hubert\\fairseq-old\\fairseq\\logging\\progress_bar.py", "source_location": "L302", "weight": 1.0}, {"source": "logging_progress_bar_tqdmprogressbar", "target": "logging_progress_bar_tqdmprogressbar_print", "relation": "method", "confidence": "EXTRACTED", "source_file": "C:\\t309\\detectors\\AVH-Align\\av_hubert\\fairseq-old\\fairseq\\logging\\progress_bar.py", "source_location": "L306", "weight": 1.0}, {"source": "c_t309_detectors_avh_align_av_hubert_fairseq_old_fairseq_logging_progress_bar_py", "target": "torch_utils_tensorboard", "relation": "imports_from", "context": "import", "confidence": "EXTRACTED", "source_file": "C:\\t309\\detectors\\AVH-Align\\av_hubert\\fairseq-old\\fairseq\\logging\\progress_bar.py", "source_location": "L315", "weight": 1.0}, {"source": "c_t309_detectors_avh_align_av_hubert_fairseq_old_fairseq_logging_progress_bar_py", "target": "tensorboardx", "relation": "imports_from", "context": "import", "confidence": "EXTRACTED", "source_file": "C:\\t309\\detectors\\AVH-Align\\av_hubert\\fairseq-old\\fairseq\\logging\\progress_bar.py", "source_location": "L318", "weight": 1.0}, {"source": "c_t309_detectors_avh_align_av_hubert_fairseq_old_fairseq_logging_progress_bar_py", "target": "logging_progress_bar_close_writers", "relation": "contains", "confidence": "EXTRACTED", "source_file": "C:\\t309\\detectors\\AVH-Align\\av_hubert\\fairseq-old\\fairseq\\logging\\progress_bar.py", "source_location": "L323", "weight": 1.0}, {"source": "c_t309_detectors_avh_align_av_hubert_fairseq_old_fairseq_logging_progress_bar_py", "target": "logging_progress_bar_tensorboardprogressbarwrapper", "relation": "contains", "confidence": "EXTRACTED", "source_file": "C:\\t309\\detectors\\AVH-Align\\av_hubert\\fairseq-old\\fairseq\\logging\\progress_bar.py", "source_location": "L331", "weight": 1.0}, {"source": "logging_progress_bar_tensorboardprogressbarwrapper", "target": "logging_progress_bar_baseprogressbar", "relation": "inherits", "confidence": "EXTRACTED", "source_file": "C:\\t309\\detectors\\AVH-Align\\av_hubert\\fairseq-old\\fairseq\\logging\\progress_bar.py", "source_location": "L331", "weight": 1.0}, {"source": "logging_progress_bar_tensorboardprogressbarwrapper", "target": "logging_progress_bar_tensorboardprogressbarwrapper_init", "relation": "method", "confidence": "EXTRACTED", "source_file": "C:\\t309\\detectors\\AVH-Align\\av_hubert\\fairseq-old\\fairseq\\logging\\progress_bar.py", "source_location": "L334", "weight": 1.0}, {"source": "logging_progress_bar_tensorboardprogressbarwrapper", "target": "logging_progress_bar_tensorboardprogressbarwrapper_writer", "relation": "method", "confidence": "EXTRACTED", "source_file": "C:\\t309\\detectors\\AVH-Align\\av_hubert\\fairseq-old\\fairseq\\logging\\progress_bar.py", "source_location": "L343", "weight": 1.0}, {"source": "logging_progress_bar_tensorboardprogressbarwrapper", "target": "logging_progress_bar_tensorboardprogressbarwrapper_iter", "relation": "method", "confidence": "EXTRACTED", "source_file": "C:\\t309\\detectors\\AVH-Align\\av_hubert\\fairseq-old\\fairseq\\logging\\progress_bar.py", "source_location": "L352", "weight": 1.0}, {"source": "logging_progress_bar_tensorboardprogressbarwrapper", "target": "logging_progress_bar_tensorboardprogressbarwrapper_log", "relation": "method", "confidence": "EXTRACTED", "source_file": "C:\\t309\\detectors\\AVH-Align\\av_hubert\\fairseq-old\\fairseq\\logging\\progress_bar.py", "source_location": "L355", "weight": 1.0}, {"source": "logging_progress_bar_tensorboardprogressbarwrapper", "target": "logging_progress_bar_tensorboardprogressbarwrapper_print", "relation": "method", "confidence": "EXTRACTED", "source_file": "C:\\t309\\detectors\\AVH-Align\\av_hubert\\fairseq-old\\fairseq\\logging\\progress_bar.py", "source_location": "L360", "weight": 1.0}, {"source": "logging_progress_bar_tensorboardprogressbarwrapper", "target": "logging_progress_bar_tensorboardprogressbarwrapper_update_config", "relation": "method", "confidence": "EXTRACTED", "source_file": "C:\\t309\\detectors\\AVH-Align\\av_hubert\\fairseq-old\\fairseq\\logging\\progress_bar.py", "source_location": "L365", "weight": 1.0}, {"source": "logging_progress_bar_tensorboardprogressbarwrapper", "target": "logging_progress_bar_tensorboardprogressbarwrapper_log_to_tensorboard", "relation": "method", "confidence": "EXTRACTED", "source_file": "C:\\t309\\detectors\\AVH-Align\\av_hubert\\fairseq-old\\fairseq\\logging\\progress_bar.py", "source_location": "L370", "weight": 1.0}, {"source": "c_t309_detectors_avh_align_av_hubert_fairseq_old_fairseq_logging_progress_bar_py", "target": "wandb", "relation": "imports", "context": "import", "confidence": "EXTRACTED", "source_file": "C:\\t309\\detectors\\AVH-Align\\av_hubert\\fairseq-old\\fairseq\\logging\\progress_bar.py", "source_location": "L387", "weight": 1.0}, {"source": "c_t309_detectors_avh_align_av_hubert_fairseq_old_fairseq_logging_progress_bar_py", "target": "logging_progress_bar_wandbprogressbarwrapper", "relation": "contains", "confidence": "EXTRACTED", "source_file": "C:\\t309\\detectors\\AVH-Align\\av_hubert\\fairseq-old\\fairseq\\logging\\progress_bar.py", "source_location": "L392", "weight": 1.0}, {"source": "logging_progress_bar_wandbprogressbarwrapper", "target": "logging_progress_bar_baseprogressbar", "relation": "inherits", "confidence": "EXTRACTED", "source_file": "C:\\t309\\detectors\\AVH-Align\\av_hubert\\fairseq-old\\fairseq\\logging\\progress_bar.py", "source_location": "L392", "weight": 1.0}, {"source": "logging_progress_bar_wandbprogressbarwrapper", "target": "logging_progress_bar_wandbprogressbarwrapper_init", "relation": "method", "confidence": "EXTRACTED", "source_file": "C:\\t309\\detectors\\AVH-Align\\av_hubert\\fairseq-old\\fairseq\\logging\\progress_bar.py", "source_location": "L395", "weight": 1.0}, {"source": "logging_progress_bar_wandbprogressbarwrapper", "target": "logging_progress_bar_wandbprogressbarwrapper_iter", "relation": "method", "confidence": "EXTRACTED", "source_file": "C:\\t309\\detectors\\AVH-Align\\av_hubert\\fairseq-old\\fairseq\\logging\\progress_bar.py", "source_location": "L405", "weight": 1.0}, {"source": "logging_progress_bar_wandbprogressbarwrapper", "target": "logging_progress_bar_wandbprogressbarwrapper_log", "relation": "method", "confidence": "EXTRACTED", "source_file": "C:\\t309\\detectors\\AVH-Align\\av_hubert\\fairseq-old\\fairseq\\logging\\progress_bar.py", "source_location": "L408", "weight": 1.0}, {"source": "logging_progress_bar_wandbprogressbarwrapper", "target": "logging_progress_bar_wandbprogressbarwrapper_print", "relation": "method", "confidence": "EXTRACTED", "source_file": "C:\\t309\\detectors\\AVH-Align\\av_hubert\\fairseq-old\\fairseq\\logging\\progress_bar.py", "source_location": "L413", "weight": 1.0}, {"source": "logging_progress_bar_wandbprogressbarwrapper", "target": "logging_progress_bar_wandbprogressbarwrapper_update_config", "relation": "method", "confidence": "EXTRACTED", "source_file": "C:\\t309\\detectors\\AVH-Align\\av_hubert\\fairseq-old\\fairseq\\logging\\progress_bar.py", "source_location": "L418", "weight": 1.0}, {"source": "logging_progress_bar_wandbprogressbarwrapper", "target": "logging_progress_bar_wandbprogressbarwrapper_log_to_wandb", "relation": "method", "confidence": "EXTRACTED", "source_file": "C:\\t309\\detectors\\AVH-Align\\av_hubert\\fairseq-old\\fairseq\\logging\\progress_bar.py", "source_location": "L424", "weight": 1.0}, {"source": "c_t309_detectors_avh_align_av_hubert_fairseq_old_fairseq_logging_progress_bar_py", "target": "azureml_core", "relation": "imports_from", "context": "import", "confidence": "EXTRACTED", "source_file": "C:\\t309\\detectors\\AVH-Align\\av_hubert\\fairseq-old\\fairseq\\logging\\progress_bar.py", "source_location": "L440", "weight": 1.0}, {"source": "c_t309_detectors_avh_align_av_hubert_fairseq_old_fairseq_logging_progress_bar_py", "target": "logging_progress_bar_azuremlprogressbarwrapper", "relation": "contains", "confidence": "EXTRACTED", "source_file": "C:\\t309\\detectors\\AVH-Align\\av_hubert\\fairseq-old\\fairseq\\logging\\progress_bar.py", "source_location": "L445", "weight": 1.0}, {"source": "logging_progress_bar_azuremlprogressbarwrapper", "target": "logging_progress_bar_baseprogressbar", "relation": "inherits", "confidence": "EXTRACTED", "source_file": "C:\\t309\\detectors\\AVH-Align\\av_hubert\\fairseq-old\\fairseq\\logging\\progress_bar.py", "source_location": "L445", "weight": 1.0}, {"source": "logging_progress_bar_azuremlprogressbarwrapper", "target": "logging_progress_bar_azuremlprogressbarwrapper_init", "relation": "method", "confidence": "EXTRACTED", "source_file": "C:\\t309\\detectors\\AVH-Align\\av_hubert\\fairseq-old\\fairseq\\logging\\progress_bar.py", "source_location": "L448", "weight": 1.0}, {"source": "logging_progress_bar_azuremlprogressbarwrapper", "target": "logging_progress_bar_azuremlprogressbarwrapper_exit", "relation": "method", "confidence": "EXTRACTED", "source_file": "C:\\t309\\detectors\\AVH-Align\\av_hubert\\fairseq-old\\fairseq\\logging\\progress_bar.py", "source_location": "L455", "weight": 1.0}, {"source": "logging_progress_bar_azuremlprogressbarwrapper", "target": "logging_progress_bar_azuremlprogressbarwrapper_iter", "relation": "method", "confidence": "EXTRACTED", "source_file": "C:\\t309\\detectors\\AVH-Align\\av_hubert\\fairseq-old\\fairseq\\logging\\progress_bar.py", "source_location": "L460", "weight": 1.0}, {"source": "logging_progress_bar_azuremlprogressbarwrapper", "target": "logging_progress_bar_azuremlprogressbarwrapper_log", "relation": "method", "confidence": "EXTRACTED", "source_file": "C:\\t309\\detectors\\AVH-Align\\av_hubert\\fairseq-old\\fairseq\\logging\\progress_bar.py", "source_location": "L463", "weight": 1.0}, {"source": "logging_progress_bar_azuremlprogressbarwrapper", "target": "logging_progress_bar_azuremlprogressbarwrapper_print", "relation": "method", "confidence": "EXTRACTED", "source_file": "C:\\t309\\detectors\\AVH-Align\\av_hubert\\fairseq-old\\fairseq\\logging\\progress_bar.py", "source_location": "L468", "weight": 1.0}, {"source": "logging_progress_bar_azuremlprogressbarwrapper", "target": "logging_progress_bar_azuremlprogressbarwrapper_update_config", "relation": "method", "confidence": "EXTRACTED", "source_file": "C:\\t309\\detectors\\AVH-Align\\av_hubert\\fairseq-old\\fairseq\\logging\\progress_bar.py", "source_location": "L473", "weight": 1.0}, {"source": "logging_progress_bar_azuremlprogressbarwrapper", "target": "logging_progress_bar_azuremlprogressbarwrapper_log_to_azureml", "relation": "method", "confidence": "EXTRACTED", "source_file": "C:\\t309\\detectors\\AVH-Align\\av_hubert\\fairseq-old\\fairseq\\logging\\progress_bar.py", "source_location": "L477", "weight": 1.0}, {"source": "logging_progress_bar_progress_bar", "target": "logging_progress_bar_jsonprogressbar", "relation": "calls", "context": "call", "confidence": "EXTRACTED", "source_file": "C:\\t309\\detectors\\AVH-Align\\av_hubert\\fairseq-old\\fairseq\\logging\\progress_bar.py", "source_location": "L51", "weight": 1.0}, {"source": "logging_progress_bar_progress_bar", "target": "logging_progress_bar_noopprogressbar", "relation": "calls", "context": "call", "confidence": "EXTRACTED", "source_file": "C:\\t309\\detectors\\AVH-Align\\av_hubert\\fairseq-old\\fairseq\\logging\\progress_bar.py", "source_location": "L53", "weight": 1.0}, {"source": "logging_progress_bar_progress_bar", "target": "logging_progress_bar_simpleprogressbar", "relation": "calls", "context": "call", "confidence": "EXTRACTED", "source_file": "C:\\t309\\detectors\\AVH-Align\\av_hubert\\fairseq-old\\fairseq\\logging\\progress_bar.py", "source_location": "L55", "weight": 1.0}, {"source": "logging_progress_bar_progress_bar", "target": "logging_progress_bar_tqdmprogressbar", "relation": "calls", "context": "call", "confidence": "EXTRACTED", "source_file": "C:\\t309\\detectors\\AVH-Align\\av_hubert\\fairseq-old\\fairseq\\logging\\progress_bar.py", "source_location": "L57", "weight": 1.0}, {"source": "logging_progress_bar_progress_bar", "target": "logging_progress_bar_tensorboardprogressbarwrapper", "relation": "calls", "context": "call", "confidence": "EXTRACTED", "source_file": "C:\\t309\\detectors\\AVH-Align\\av_hubert\\fairseq-old\\fairseq\\logging\\progress_bar.py", "source_location": "L69", "weight": 1.0}, {"source": "logging_progress_bar_progress_bar", "target": "logging_progress_bar_wandbprogressbarwrapper", "relation": "calls", "context": "call", "confidence": "EXTRACTED", "source_file": "C:\\t309\\detectors\\AVH-Align\\av_hubert\\fairseq-old\\fairseq\\logging\\progress_bar.py", "source_location": "L72", "weight": 1.0}, {"source": "logging_progress_bar_progress_bar", "target": "logging_progress_bar_azuremlprogressbarwrapper", "relation": "calls", "context": "call", "confidence": "EXTRACTED", "source_file": "C:\\t309\\detectors\\AVH-Align\\av_hubert\\fairseq-old\\fairseq\\logging\\progress_bar.py", "source_location": "L75", "weight": 1.0}, {"source": "logging_progress_bar_build_progress_bar", "target": "logging_progress_bar_progress_bar", "relation": "calls", "context": "call", "confidence": "EXTRACTED", "source_file": "C:\\t309\\detectors\\AVH-Align\\av_hubert\\fairseq-old\\fairseq\\logging\\progress_bar.py", "source_location": "L95", "weight": 1.0}, {"source": "logging_progress_bar_baseprogressbar_format_stats", "target": "logging_progress_bar_format_stat", "relation": "calls", "context": "call", "confidence": "EXTRACTED", "source_file": "C:\\t309\\detectors\\AVH-Align\\av_hubert\\fairseq-old\\fairseq\\logging\\progress_bar.py", "source_location": "L167", "weight": 1.0}, {"source": "logging_progress_bar_jsonprogressbar_init", "target": "logging_progress_bar_azuremlprogressbarwrapper_init", "relation": "calls", "context": "call", "confidence": "EXTRACTED", "source_file": "C:\\t309\\detectors\\AVH-Align\\av_hubert\\fairseq-old\\fairseq\\logging\\progress_bar.py", "source_location": "L184", "weight": 1.0}, {"source": "logging_progress_bar_jsonprogressbar_log", "target": "logging_progress_bar_jsonprogressbar_format_stats", "relation": "calls", "context": "call", "confidence": "EXTRACTED", "source_file": "C:\\t309\\detectors\\AVH-Align\\av_hubert\\fairseq-old\\fairseq\\logging\\progress_bar.py", "source_location": "L204", "weight": 1.0}, {"source": "logging_progress_bar_jsonprogressbar_log", "target": "logging_progress_bar_rename_logger", "relation": "calls", "context": "call", "confidence": "EXTRACTED", "source_file": "C:\\t309\\detectors\\AVH-Align\\av_hubert\\fairseq-old\\fairseq\\logging\\progress_bar.py", "source_location": "L205", "weight": 1.0}, {"source": "logging_progress_bar_jsonprogressbar_print", "target": "logging_progress_bar_jsonprogressbar_format_stats", "relation": "calls", "context": "call", "confidence": "EXTRACTED", "source_file": "C:\\t309\\detectors\\AVH-Align\\av_hubert\\fairseq-old\\fairseq\\logging\\progress_bar.py", "source_location": "L215", "weight": 1.0}, {"source": "logging_progress_bar_jsonprogressbar_print", "target": "logging_progress_bar_rename_logger", "relation": "calls", "context": "call", "confidence": "EXTRACTED", "source_file": "C:\\t309\\detectors\\AVH-Align\\av_hubert\\fairseq-old\\fairseq\\logging\\progress_bar.py", "source_location": "L216", "weight": 1.0}, {"source": "logging_progress_bar_jsonprogressbar_format_stats", "target": "logging_progress_bar_format_stat", "relation": "calls", "context": "call", "confidence": "EXTRACTED", "source_file": "C:\\t309\\detectors\\AVH-Align\\av_hubert\\fairseq-old\\fairseq\\logging\\progress_bar.py", "source_location": "L227", "weight": 1.0}, {"source": "logging_progress_bar_noopprogressbar_init", "target": "logging_progress_bar_azuremlprogressbarwrapper_init", "relation": "calls", "context": "call", "confidence": "EXTRACTED", "source_file": "C:\\t309\\detectors\\AVH-Align\\av_hubert\\fairseq-old\\fairseq\\logging\\progress_bar.py", "source_location": "L235", "weight": 1.0}, {"source": "logging_progress_bar_simpleprogressbar_init", "target": "logging_progress_bar_azuremlprogressbarwrapper_init", "relation": "calls", "context": "call", "confidence": "EXTRACTED", "source_file": "C:\\t309\\detectors\\AVH-Align\\av_hubert\\fairseq-old\\fairseq\\logging\\progress_bar.py", "source_location": "L254", "weight": 1.0}, {"source": "logging_progress_bar_simpleprogressbar_log", "target": "logging_progress_bar_jsonprogressbar_format_stats", "relation": "calls", "context": "call", "confidence": "EXTRACTED", "source_file": "C:\\t309\\detectors\\AVH-Align\\av_hubert\\fairseq-old\\fairseq\\logging\\progress_bar.py", "source_location": "L269", "weight": 1.0}, {"source": "logging_progress_bar_simpleprogressbar_log", "target": "logging_progress_bar_baseprogressbar_str_commas", "relation": "calls", "context": "call", "confidence": "EXTRACTED", "source_file": "C:\\t309\\detectors\\AVH-Align\\av_hubert\\fairseq-old\\fairseq\\logging\\progress_bar.py", "source_location": "L270", "weight": 1.0}, {"source": "logging_progress_bar_simpleprogressbar_log", "target": "logging_progress_bar_rename_logger", "relation": "calls", "context": "call", "confidence": "EXTRACTED", "source_file": "C:\\t309\\detectors\\AVH-Align\\av_hubert\\fairseq-old\\fairseq\\logging\\progress_bar.py", "source_location": "L271", "weight": 1.0}, {"source": "logging_progress_bar_simpleprogressbar_print", "target": "logging_progress_bar_baseprogressbar_str_pipes", "relation": "calls", "context": "call", "confidence": "EXTRACTED", "source_file": "C:\\t309\\detectors\\AVH-Align\\av_hubert\\fairseq-old\\fairseq\\logging\\progress_bar.py", "source_location": "L280", "weight": 1.0}, {"source": "logging_progress_bar_simpleprogressbar_print", "target": "logging_progress_bar_jsonprogressbar_format_stats", "relation": "calls", "context": "call", "confidence": "EXTRACTED", "source_file": "C:\\t309\\detectors\\AVH-Align\\av_hubert\\fairseq-old\\fairseq\\logging\\progress_bar.py", "source_location": "L280", "weight": 1.0}, {"source": "logging_progress_bar_simpleprogressbar_print", "target": "logging_progress_bar_rename_logger", "relation": "calls", "context": "call", "confidence": "EXTRACTED", "source_file": "C:\\t309\\detectors\\AVH-Align\\av_hubert\\fairseq-old\\fairseq\\logging\\progress_bar.py", "source_location": "L281", "weight": 1.0}, {"source": "logging_progress_bar_tqdmprogressbar_init", "target": "logging_progress_bar_azuremlprogressbarwrapper_init", "relation": "calls", "context": "call", "confidence": "EXTRACTED", "source_file": "C:\\t309\\detectors\\AVH-Align\\av_hubert\\fairseq-old\\fairseq\\logging\\progress_bar.py", "source_location": "L289", "weight": 1.0}, {"source": "logging_progress_bar_tqdmprogressbar_log", "target": "logging_progress_bar_jsonprogressbar_format_stats", "relation": "calls", "context": "call", "confidence": "EXTRACTED", "source_file": "C:\\t309\\detectors\\AVH-Align\\av_hubert\\fairseq-old\\fairseq\\logging\\progress_bar.py", "source_location": "L304", "weight": 1.0}, {"source": "logging_progress_bar_tqdmprogressbar_print", "target": "logging_progress_bar_baseprogressbar_str_pipes", "relation": "calls", "context": "call", "confidence": "EXTRACTED", "source_file": "C:\\t309\\detectors\\AVH-Align\\av_hubert\\fairseq-old\\fairseq\\logging\\progress_bar.py", "source_location": "L308", "weight": 1.0}, {"source": "logging_progress_bar_tqdmprogressbar_print", "target": "logging_progress_bar_jsonprogressbar_format_stats", "relation": "calls", "context": "call", "confidence": "EXTRACTED", "source_file": "C:\\t309\\detectors\\AVH-Align\\av_hubert\\fairseq-old\\fairseq\\logging\\progress_bar.py", "source_location": "L308", "weight": 1.0}, {"source": "logging_progress_bar_tqdmprogressbar_print", "target": "logging_progress_bar_rename_logger", "relation": "calls", "context": "call", "confidence": "EXTRACTED", "source_file": "C:\\t309\\detectors\\AVH-Align\\av_hubert\\fairseq-old\\fairseq\\logging\\progress_bar.py", "source_location": "L309", "weight": 1.0}, {"source": "logging_progress_bar_tensorboardprogressbarwrapper_log", "target": "logging_progress_bar_tensorboardprogressbarwrapper_log_to_tensorboard", "relation": "calls", "context": "call", "confidence": "EXTRACTED", "source_file": "C:\\t309\\detectors\\AVH-Align\\av_hubert\\fairseq-old\\fairseq\\logging\\progress_bar.py", "source_location": "L357", "weight": 1.0}, {"source": "logging_progress_bar_tensorboardprogressbarwrapper_log", "target": "logging_progress_bar_azuremlprogressbarwrapper_log", "relation": "calls", "context": "call", "confidence": "EXTRACTED", "source_file": "C:\\t309\\detectors\\AVH-Align\\av_hubert\\fairseq-old\\fairseq\\logging\\progress_bar.py", "source_location": "L358", "weight": 1.0}, {"source": "logging_progress_bar_tensorboardprogressbarwrapper_print", "target": "logging_progress_bar_tensorboardprogressbarwrapper_log_to_tensorboard", "relation": "calls", "context": "call", "confidence": "EXTRACTED", "source_file": "C:\\t309\\detectors\\AVH-Align\\av_hubert\\fairseq-old\\fairseq\\logging\\progress_bar.py", "source_location": "L362", "weight": 1.0}, {"source": "logging_progress_bar_tensorboardprogressbarwrapper_print", "target": "logging_progress_bar_azuremlprogressbarwrapper_print", "relation": "calls", "context": "call", "confidence": "EXTRACTED", "source_file": "C:\\t309\\detectors\\AVH-Align\\av_hubert\\fairseq-old\\fairseq\\logging\\progress_bar.py", "source_location": "L363", "weight": 1.0}, {"source": "logging_progress_bar_tensorboardprogressbarwrapper_update_config", "target": "logging_progress_bar_azuremlprogressbarwrapper_update_config", "relation": "calls", "context": "call", "confidence": "EXTRACTED", "source_file": "C:\\t309\\detectors\\AVH-Align\\av_hubert\\fairseq-old\\fairseq\\logging\\progress_bar.py", "source_location": "L368", "weight": 1.0}, {"source": "logging_progress_bar_tensorboardprogressbarwrapper_log_to_tensorboard", "target": "logging_progress_bar_tensorboardprogressbarwrapper_writer", "relation": "calls", "context": "call", "confidence": "EXTRACTED", "source_file": "C:\\t309\\detectors\\AVH-Align\\av_hubert\\fairseq-old\\fairseq\\logging\\progress_bar.py", "source_location": "L371", "weight": 1.0}, {"source": "logging_progress_bar_wandbprogressbarwrapper_log", "target": "logging_progress_bar_wandbprogressbarwrapper_log_to_wandb", "relation": "calls", "context": "call", "confidence": "EXTRACTED", "source_file": "C:\\t309\\detectors\\AVH-Align\\av_hubert\\fairseq-old\\fairseq\\logging\\progress_bar.py", "source_location": "L410", "weight": 1.0}, {"source": "logging_progress_bar_wandbprogressbarwrapper_log", "target": "logging_progress_bar_azuremlprogressbarwrapper_log", "relation": "calls", "context": "call", "confidence": "EXTRACTED", "source_file": "C:\\t309\\detectors\\AVH-Align\\av_hubert\\fairseq-old\\fairseq\\logging\\progress_bar.py", "source_location": "L411", "weight": 1.0}, {"source": "logging_progress_bar_wandbprogressbarwrapper_print", "target": "logging_progress_bar_wandbprogressbarwrapper_log_to_wandb", "relation": "calls", "context": "call", "confidence": "EXTRACTED", "source_file": "C:\\t309\\detectors\\AVH-Align\\av_hubert\\fairseq-old\\fairseq\\logging\\progress_bar.py", "source_location": "L415", "weight": 1.0}, {"source": "logging_progress_bar_wandbprogressbarwrapper_print", "target": "logging_progress_bar_azuremlprogressbarwrapper_print", "relation": "calls", "context": "call", "confidence": "EXTRACTED", "source_file": "C:\\t309\\detectors\\AVH-Align\\av_hubert\\fairseq-old\\fairseq\\logging\\progress_bar.py", "source_location": "L416", "weight": 1.0}, {"source": "logging_progress_bar_wandbprogressbarwrapper_update_config", "target": "logging_progress_bar_azuremlprogressbarwrapper_update_config", "relation": "calls", "context": "call", "confidence": "EXTRACTED", "source_file": "C:\\t309\\detectors\\AVH-Align\\av_hubert\\fairseq-old\\fairseq\\logging\\progress_bar.py", "source_location": "L422", "weight": 1.0}, {"source": "logging_progress_bar_wandbprogressbarwrapper_log_to_wandb", "target": "logging_progress_bar_azuremlprogressbarwrapper_log", "relation": "calls", "context": "call", "confidence": "EXTRACTED", "source_file": "C:\\t309\\detectors\\AVH-Align\\av_hubert\\fairseq-old\\fairseq\\logging\\progress_bar.py", "source_location": "L434", "weight": 1.0}, {"source": "logging_progress_bar_azuremlprogressbarwrapper_log", "target": "logging_progress_bar_azuremlprogressbarwrapper_log_to_azureml", "relation": "calls", "context": "call", "confidence": "EXTRACTED", "source_file": "C:\\t309\\detectors\\AVH-Align\\av_hubert\\fairseq-old\\fairseq\\logging\\progress_bar.py", "source_location": "L465", "weight": 1.0}, {"source": "logging_progress_bar_azuremlprogressbarwrapper_print", "target": "logging_progress_bar_azuremlprogressbarwrapper_log_to_azureml", "relation": "calls", "context": "call", "confidence": "EXTRACTED", "source_file": "C:\\t309\\detectors\\AVH-Align\\av_hubert\\fairseq-old\\fairseq\\logging\\progress_bar.py", "source_location": "L470", "weight": 1.0}, {"source": "logging_progress_bar_rationale_88", "target": "logging_progress_bar_build_progress_bar", "relation": "rationale_for", "confidence": "EXTRACTED", "source_file": "C:\\t309\\detectors\\AVH-Align\\av_hubert\\fairseq-old\\fairseq\\logging\\progress_bar.py", "source_location": "L88", "weight": 1.0}, {"source": "logging_progress_bar_rationale_121", "target": "logging_progress_bar_baseprogressbar", "relation": "rationale_for", "confidence": "EXTRACTED", "source_file": "C:\\t309\\detectors\\AVH-Align\\av_hubert\\fairseq-old\\fairseq\\logging\\progress_bar.py", "source_location": "L121", "weight": 1.0}, {"source": "logging_progress_bar_rationale_146", "target": "logging_progress_bar_baseprogressbar_log", "relation": "rationale_for", "confidence": "EXTRACTED", "source_file": "C:\\t309\\detectors\\AVH-Align\\av_hubert\\fairseq-old\\fairseq\\logging\\progress_bar.py", "source_location": "L146", "weight": 1.0}, {"source": "logging_progress_bar_rationale_150", "target": "logging_progress_bar_baseprogressbar_print", "relation": "rationale_for", "confidence": "EXTRACTED", "source_file": "C:\\t309\\detectors\\AVH-Align\\av_hubert\\fairseq-old\\fairseq\\logging\\progress_bar.py", "source_location": "L150", "weight": 1.0}, {"source": "logging_progress_bar_rationale_154", "target": "logging_progress_bar_baseprogressbar_update_config", "relation": "rationale_for", "confidence": "EXTRACTED", "source_file": "C:\\t309\\detectors\\AVH-Align\\av_hubert\\fairseq-old\\fairseq\\logging\\progress_bar.py", "source_location": "L154", "weight": 1.0}, {"source": "logging_progress_bar_rationale_181", "target": "logging_progress_bar_jsonprogressbar", "relation": "rationale_for", "confidence": "EXTRACTED", "source_file": "C:\\t309\\detectors\\AVH-Align\\av_hubert\\fairseq-old\\fairseq\\logging\\progress_bar.py", "source_location": "L181", "weight": 1.0}, {"source": "logging_progress_bar_rationale_196", "target": "logging_progress_bar_jsonprogressbar_log", "relation": "rationale_for", "confidence": "EXTRACTED", "source_file": "C:\\t309\\detectors\\AVH-Align\\av_hubert\\fairseq-old\\fairseq\\logging\\progress_bar.py", "source_location": "L196", "weight": 1.0}, {"source": "logging_progress_bar_rationale_209", "target": "logging_progress_bar_jsonprogressbar_print", "relation": "rationale_for", "confidence": "EXTRACTED", "source_file": "C:\\t309\\detectors\\AVH-Align\\av_hubert\\fairseq-old\\fairseq\\logging\\progress_bar.py", "source_location": "L209", "weight": 1.0}, {"source": "logging_progress_bar_rationale_242", "target": "logging_progress_bar_noopprogressbar_log", "relation": "rationale_for", "confidence": "EXTRACTED", "source_file": "C:\\t309\\detectors\\AVH-Align\\av_hubert\\fairseq-old\\fairseq\\logging\\progress_bar.py", "source_location": "L242", "weight": 1.0}, {"source": "logging_progress_bar_rationale_246", "target": "logging_progress_bar_noopprogressbar_print", "relation": "rationale_for", "confidence": "EXTRACTED", "source_file": "C:\\t309\\detectors\\AVH-Align\\av_hubert\\fairseq-old\\fairseq\\logging\\progress_bar.py", "source_location": "L246", "weight": 1.0}, {"source": "logging_progress_bar_rationale_251", "target": "logging_progress_bar_simpleprogressbar", "relation": "rationale_for", "confidence": "EXTRACTED", "source_file": "C:\\t309\\detectors\\AVH-Align\\av_hubert\\fairseq-old\\fairseq\\logging\\progress_bar.py", "source_location": "L251", "weight": 1.0}, {"source": "logging_progress_bar_rationale_266", "target": "logging_progress_bar_simpleprogressbar_log", "relation": "rationale_for", "confidence": "EXTRACTED", "source_file": "C:\\t309\\detectors\\AVH-Align\\av_hubert\\fairseq-old\\fairseq\\logging\\progress_bar.py", "source_location": "L266", "weight": 1.0}, {"source": "logging_progress_bar_rationale_279", "target": "logging_progress_bar_simpleprogressbar_print", "relation": "rationale_for", "confidence": "EXTRACTED", "source_file": "C:\\t309\\detectors\\AVH-Align\\av_hubert\\fairseq-old\\fairseq\\logging\\progress_bar.py", "source_location": "L279", "weight": 1.0}, {"source": "logging_progress_bar_rationale_303", "target": "logging_progress_bar_tqdmprogressbar_log", "relation": "rationale_for", "confidence": "EXTRACTED", "source_file": "C:\\t309\\detectors\\AVH-Align\\av_hubert\\fairseq-old\\fairseq\\logging\\progress_bar.py", "source_location": "L303", "weight": 1.0}, {"source": "logging_progress_bar_rationale_307", "target": "logging_progress_bar_tqdmprogressbar_print", "relation": "rationale_for", "confidence": "EXTRACTED", "source_file": "C:\\t309\\detectors\\AVH-Align\\av_hubert\\fairseq-old\\fairseq\\logging\\progress_bar.py", "source_location": "L307", "weight": 1.0}, {"source": "logging_progress_bar_rationale_356", "target": "logging_progress_bar_tensorboardprogressbarwrapper_log", "relation": "rationale_for", "confidence": "EXTRACTED", "source_file": "C:\\t309\\detectors\\AVH-Align\\av_hubert\\fairseq-old\\fairseq\\logging\\progress_bar.py", "source_location": "L356", "weight": 1.0}, {"source": "logging_progress_bar_rationale_361", "target": "logging_progress_bar_tensorboardprogressbarwrapper_print", "relation": "rationale_for", "confidence": "EXTRACTED", "source_file": "C:\\t309\\detectors\\AVH-Align\\av_hubert\\fairseq-old\\fairseq\\logging\\progress_bar.py", "source_location": "L361", "weight": 1.0}, {"source": "logging_progress_bar_rationale_366", "target": "logging_progress_bar_tensorboardprogressbarwrapper_update_config", "relation": "rationale_for", "confidence": "EXTRACTED", "source_file": "C:\\t309\\detectors\\AVH-Align\\av_hubert\\fairseq-old\\fairseq\\logging\\progress_bar.py", "source_location": "L366", "weight": 1.0}, {"source": "logging_progress_bar_rationale_393", "target": "logging_progress_bar_wandbprogressbarwrapper", "relation": "rationale_for", "confidence": "EXTRACTED", "source_file": "C:\\t309\\detectors\\AVH-Align\\av_hubert\\fairseq-old\\fairseq\\logging\\progress_bar.py", "source_location": "L393", "weight": 1.0}, {"source": "logging_progress_bar_rationale_409", "target": "logging_progress_bar_wandbprogressbarwrapper_log", "relation": "rationale_for", "confidence": "EXTRACTED", "source_file": "C:\\t309\\detectors\\AVH-Align\\av_hubert\\fairseq-old\\fairseq\\logging\\progress_bar.py", "source_location": "L409", "weight": 1.0}, {"source": "logging_progress_bar_rationale_414", "target": "logging_progress_bar_wandbprogressbarwrapper_print", "relation": "rationale_for", "confidence": "EXTRACTED", "source_file": "C:\\t309\\detectors\\AVH-Align\\av_hubert\\fairseq-old\\fairseq\\logging\\progress_bar.py", "source_location": "L414", "weight": 1.0}, {"source": "logging_progress_bar_rationale_419", "target": "logging_progress_bar_wandbprogressbarwrapper_update_config", "relation": "rationale_for", "confidence": "EXTRACTED", "source_file": "C:\\t309\\detectors\\AVH-Align\\av_hubert\\fairseq-old\\fairseq\\logging\\progress_bar.py", "source_location": "L419", "weight": 1.0}, {"source": "logging_progress_bar_rationale_464", "target": "logging_progress_bar_azuremlprogressbarwrapper_log", "relation": "rationale_for", "confidence": "EXTRACTED", "source_file": "C:\\t309\\detectors\\AVH-Align\\av_hubert\\fairseq-old\\fairseq\\logging\\progress_bar.py", "source_location": "L464", "weight": 1.0}, {"source": "logging_progress_bar_rationale_469", "target": "logging_progress_bar_azuremlprogressbarwrapper_print", "relation": "rationale_for", "confidence": "EXTRACTED", "source_file": "C:\\t309\\detectors\\AVH-Align\\av_hubert\\fairseq-old\\fairseq\\logging\\progress_bar.py", "source_location": "L469", "weight": 1.0}, {"source": "logging_progress_bar_rationale_474", "target": "logging_progress_bar_azuremlprogressbarwrapper_update_config", "relation": "rationale_for", "confidence": "EXTRACTED", "source_file": "C:\\t309\\detectors\\AVH-Align\\av_hubert\\fairseq-old\\fairseq\\logging\\progress_bar.py", "source_location": "L474", "weight": 1.0}], "raw_calls": [{"caller_nid": "logging_progress_bar_progress_bar", "callee": "FileHandler", "is_member_call": true, "source_file": "C:\\t309\\detectors\\AVH-Align\\av_hubert\\fairseq-old\\fairseq\\logging\\progress_bar.py", "source_location": "L44"}, {"caller_nid": "logging_progress_bar_progress_bar", "callee": "addHandler", "is_member_call": true, "source_file": "C:\\t309\\detectors\\AVH-Align\\av_hubert\\fairseq-old\\fairseq\\logging\\progress_bar.py", "source_location": "L45"}, {"caller_nid": "logging_progress_bar_progress_bar", "callee": "isatty", "is_member_call": true, "source_file": "C:\\t309\\detectors\\AVH-Align\\av_hubert\\fairseq-old\\fairseq\\logging\\progress_bar.py", "source_location": "L47"}, {"caller_nid": "logging_progress_bar_progress_bar", "callee": "ValueError", "is_member_call": false, "source_file": "C:\\t309\\detectors\\AVH-Align\\av_hubert\\fairseq-old\\fairseq\\logging\\progress_bar.py", "source_location": "L59"}, {"caller_nid": "logging_progress_bar_progress_bar", "callee": "format", "is_member_call": true, "source_file": "C:\\t309\\detectors\\AVH-Align\\av_hubert\\fairseq-old\\fairseq\\logging\\progress_bar.py", "source_location": "L59"}, {"caller_nid": "logging_progress_bar_progress_bar", "callee": "FbTbmfWrapper", "is_member_call": false, "source_file": "C:\\t309\\detectors\\AVH-Align\\av_hubert\\fairseq-old\\fairseq\\logging\\progress_bar.py", "source_location": "L67"}, {"caller_nid": "logging_progress_bar_build_progress_bar", "callee": "getattr", "is_member_call": false, "source_file": "C:\\t309\\detectors\\AVH-Align\\av_hubert\\fairseq-old\\fairseq\\logging\\progress_bar.py", "source_location": "L89"}, {"caller_nid": "logging_progress_bar_build_progress_bar", "callee": "getattr", "is_member_call": false, "source_file": "C:\\t309\\detectors\\AVH-Align\\av_hubert\\fairseq-old\\fairseq\\logging\\progress_bar.py", "source_location": "L91"}, {"caller_nid": "logging_progress_bar_build_progress_bar", "callee": "getattr", "is_member_call": false, "source_file": "C:\\t309\\detectors\\AVH-Align\\av_hubert\\fairseq-old\\fairseq\\logging\\progress_bar.py", "source_location": "L92"}, {"caller_nid": "logging_progress_bar_format_stat", "callee": "isinstance", "is_member_call": false, "source_file": "C:\\t309\\detectors\\AVH-Align\\av_hubert\\fairseq-old\\fairseq\\logging\\progress_bar.py", "source_location": "L107"}, {"caller_nid": "logging_progress_bar_format_stat", "callee": "format", "is_member_call": true, "source_file": "C:\\t309\\detectors\\AVH-Align\\av_hubert\\fairseq-old\\fairseq\\logging\\progress_bar.py", "source_location": "L108"}, {"caller_nid": "logging_progress_bar_format_stat", "callee": "isinstance", "is_member_call": false, "source_file": "C:\\t309\\detectors\\AVH-Align\\av_hubert\\fairseq-old\\fairseq\\logging\\progress_bar.py", "source_location": "L109"}, {"caller_nid": "logging_progress_bar_format_stat", "callee": "format", "is_member_call": true, "source_file": "C:\\t309\\detectors\\AVH-Align\\av_hubert\\fairseq-old\\fairseq\\logging\\progress_bar.py", "source_location": "L110"}, {"caller_nid": "logging_progress_bar_format_stat", "callee": "isinstance", "is_member_call": false, "source_file": "C:\\t309\\detectors\\AVH-Align\\av_hubert\\fairseq-old\\fairseq\\logging\\progress_bar.py", "source_location": "L111"}, {"caller_nid": "logging_progress_bar_format_stat", "callee": "format", "is_member_call": true, "source_file": "C:\\t309\\detectors\\AVH-Align\\av_hubert\\fairseq-old\\fairseq\\logging\\progress_bar.py", "source_location": "L112"}, {"caller_nid": "logging_progress_bar_format_stat", "callee": "round", "is_member_call": false, "source_file": "C:\\t309\\detectors\\AVH-Align\\av_hubert\\fairseq-old\\fairseq\\logging\\progress_bar.py", "source_location": "L112"}, {"caller_nid": "logging_progress_bar_format_stat", "callee": "isinstance", "is_member_call": false, "source_file": "C:\\t309\\detectors\\AVH-Align\\av_hubert\\fairseq-old\\fairseq\\logging\\progress_bar.py", "source_location": "L113"}, {"caller_nid": "logging_progress_bar_format_stat", "callee": "format", "is_member_call": true, "source_file": "C:\\t309\\detectors\\AVH-Align\\av_hubert\\fairseq-old\\fairseq\\logging\\progress_bar.py", "source_location": "L114"}, {"caller_nid": "logging_progress_bar_format_stat", "callee": "round", "is_member_call": false, "source_file": "C:\\t309\\detectors\\AVH-Align\\av_hubert\\fairseq-old\\fairseq\\logging\\progress_bar.py", "source_location": "L114"}, {"caller_nid": "logging_progress_bar_format_stat", "callee": "is_tensor", "is_member_call": true, "source_file": "C:\\t309\\detectors\\AVH-Align\\av_hubert\\fairseq-old\\fairseq\\logging\\progress_bar.py", "source_location": "L115"}, {"caller_nid": "logging_progress_bar_format_stat", "callee": "tolist", "is_member_call": true, "source_file": "C:\\t309\\detectors\\AVH-Align\\av_hubert\\fairseq-old\\fairseq\\logging\\progress_bar.py", "source_location": "L116"}, {"caller_nid": "logging_progress_bar_baseprogressbar_init", "callee": "getattr", "is_member_call": false, "source_file": "C:\\t309\\detectors\\AVH-Align\\av_hubert\\fairseq-old\\fairseq\\logging\\progress_bar.py", "source_location": "L125"}, {"caller_nid": "logging_progress_bar_baseprogressbar_init", "callee": "format", "is_member_call": true, "source_file": "C:\\t309\\detectors\\AVH-Align\\av_hubert\\fairseq-old\\fairseq\\logging\\progress_bar.py", "source_location": "L129"}, {"caller_nid": "logging_progress_bar_baseprogressbar_len", "callee": "len", "is_member_call": false, "source_file": "C:\\t309\\detectors\\AVH-Align\\av_hubert\\fairseq-old\\fairseq\\logging\\progress_bar.py", "source_location": "L134"}, {"caller_nid": "logging_progress_bar_baseprogressbar_str_commas", "callee": "join", "is_member_call": true, "source_file": "C:\\t309\\detectors\\AVH-Align\\av_hubert\\fairseq-old\\fairseq\\logging\\progress_bar.py", "source_location": "L158"}, {"caller_nid": "logging_progress_bar_baseprogressbar_str_commas", "callee": "strip", "is_member_call": true, "source_file": "C:\\t309\\detectors\\AVH-Align\\av_hubert\\fairseq-old\\fairseq\\logging\\progress_bar.py", "source_location": "L158"}, {"caller_nid": "logging_progress_bar_baseprogressbar_str_commas", "callee": "keys", "is_member_call": true, "source_file": "C:\\t309\\detectors\\AVH-Align\\av_hubert\\fairseq-old\\fairseq\\logging\\progress_bar.py", "source_location": "L158"}, {"caller_nid": "logging_progress_bar_baseprogressbar_str_pipes", "callee": "join", "is_member_call": true, "source_file": "C:\\t309\\detectors\\AVH-Align\\av_hubert\\fairseq-old\\fairseq\\logging\\progress_bar.py", "source_location": "L161"}, {"caller_nid": "logging_progress_bar_baseprogressbar_str_pipes", "callee": "strip", "is_member_call": true, "source_file": "C:\\t309\\detectors\\AVH-Align\\av_hubert\\fairseq-old\\fairseq\\logging\\progress_bar.py", "source_location": "L161"}, {"caller_nid": "logging_progress_bar_baseprogressbar_str_pipes", "callee": "keys", "is_member_call": true, "source_file": "C:\\t309\\detectors\\AVH-Align\\av_hubert\\fairseq-old\\fairseq\\logging\\progress_bar.py", "source_location": "L161"}, {"caller_nid": "logging_progress_bar_baseprogressbar_format_stats", "callee": "OrderedDict", "is_member_call": false, "source_file": "C:\\t309\\detectors\\AVH-Align\\av_hubert\\fairseq-old\\fairseq\\logging\\progress_bar.py", "source_location": "L164"}, {"caller_nid": "logging_progress_bar_baseprogressbar_format_stats", "callee": "keys", "is_member_call": true, "source_file": "C:\\t309\\detectors\\AVH-Align\\av_hubert\\fairseq-old\\fairseq\\logging\\progress_bar.py", "source_location": "L166"}, {"caller_nid": "logging_progress_bar_baseprogressbar_format_stats", "callee": "str", "is_member_call": false, "source_file": "C:\\t309\\detectors\\AVH-Align\\av_hubert\\fairseq-old\\fairseq\\logging\\progress_bar.py", "source_location": "L167"}, {"caller_nid": "logging_progress_bar_jsonprogressbar_init", "callee": "super", "is_member_call": false, "source_file": "C:\\t309\\detectors\\AVH-Align\\av_hubert\\fairseq-old\\fairseq\\logging\\progress_bar.py", "source_location": "L184"}, {"caller_nid": "logging_progress_bar_jsonprogressbar_iter", "callee": "len", "is_member_call": false, "source_file": "C:\\t309\\detectors\\AVH-Align\\av_hubert\\fairseq-old\\fairseq\\logging\\progress_bar.py", "source_location": "L190"}, {"caller_nid": "logging_progress_bar_jsonprogressbar_iter", "callee": "enumerate", "is_member_call": false, "source_file": "C:\\t309\\detectors\\AVH-Align\\av_hubert\\fairseq-old\\fairseq\\logging\\progress_bar.py", "source_location": "L191"}, {"caller_nid": "logging_progress_bar_jsonprogressbar_log", "callee": "float", "is_member_call": false, "source_file": "C:\\t309\\detectors\\AVH-Align\\av_hubert\\fairseq-old\\fairseq\\logging\\progress_bar.py", "source_location": "L200"}, {"caller_nid": "logging_progress_bar_jsonprogressbar_log", "callee": "info", "is_member_call": true, "source_file": "C:\\t309\\detectors\\AVH-Align\\av_hubert\\fairseq-old\\fairseq\\logging\\progress_bar.py", "source_location": "L206"}, {"caller_nid": "logging_progress_bar_jsonprogressbar_log", "callee": "dumps", "is_member_call": true, "source_file": "C:\\t309\\detectors\\AVH-Align\\av_hubert\\fairseq-old\\fairseq\\logging\\progress_bar.py", "source_location": "L206"}, {"caller_nid": "logging_progress_bar_jsonprogressbar_print", "callee": "OrderedDict", "is_member_call": false, "source_file": "C:\\t309\\detectors\\AVH-Align\\av_hubert\\fairseq-old\\fairseq\\logging\\progress_bar.py", "source_location": "L212"}, {"caller_nid": "logging_progress_bar_jsonprogressbar_print", "callee": "items", "is_member_call": true, "source_file": "C:\\t309\\detectors\\AVH-Align\\av_hubert\\fairseq-old\\fairseq\\logging\\progress_bar.py", "source_location": "L213"}, {"caller_nid": "logging_progress_bar_jsonprogressbar_print", "callee": "info", "is_member_call": true, "source_file": "C:\\t309\\detectors\\AVH-Align\\av_hubert\\fairseq-old\\fairseq\\logging\\progress_bar.py", "source_location": "L217"}, {"caller_nid": "logging_progress_bar_jsonprogressbar_print", "callee": "dumps", "is_member_call": true, "source_file": "C:\\t309\\detectors\\AVH-Align\\av_hubert\\fairseq-old\\fairseq\\logging\\progress_bar.py", "source_location": "L217"}, {"caller_nid": "logging_progress_bar_jsonprogressbar_format_stats", "callee": "OrderedDict", "is_member_call": false, "source_file": "C:\\t309\\detectors\\AVH-Align\\av_hubert\\fairseq-old\\fairseq\\logging\\progress_bar.py", "source_location": "L220"}, {"caller_nid": "logging_progress_bar_jsonprogressbar_format_stats", "callee": "round", "is_member_call": false, "source_file": "C:\\t309\\detectors\\AVH-Align\\av_hubert\\fairseq-old\\fairseq\\logging\\progress_bar.py", "source_location": "L224"}, {"caller_nid": "logging_progress_bar_jsonprogressbar_format_stats", "callee": "keys", "is_member_call": true, "source_file": "C:\\t309\\detectors\\AVH-Align\\av_hubert\\fairseq-old\\fairseq\\logging\\progress_bar.py", "source_location": "L226"}, {"caller_nid": "logging_progress_bar_noopprogressbar_init", "callee": "super", "is_member_call": false, "source_file": "C:\\t309\\detectors\\AVH-Align\\av_hubert\\fairseq-old\\fairseq\\logging\\progress_bar.py", "source_location": "L235"}, {"caller_nid": "logging_progress_bar_simpleprogressbar_init", "callee": "super", "is_member_call": false, "source_file": "C:\\t309\\detectors\\AVH-Align\\av_hubert\\fairseq-old\\fairseq\\logging\\progress_bar.py", "source_location": "L254"}, {"caller_nid": "logging_progress_bar_simpleprogressbar_iter", "callee": "len", "is_member_call": false, "source_file": "C:\\t309\\detectors\\AVH-Align\\av_hubert\\fairseq-old\\fairseq\\logging\\progress_bar.py", "source_location": "L260"}, {"caller_nid": "logging_progress_bar_simpleprogressbar_iter", "callee": "enumerate", "is_member_call": false, "source_file": "C:\\t309\\detectors\\AVH-Align\\av_hubert\\fairseq-old\\fairseq\\logging\\progress_bar.py", "source_location": "L261"}, {"caller_nid": "logging_progress_bar_simpleprogressbar_log", "callee": "info", "is_member_call": true, "source_file": "C:\\t309\\detectors\\AVH-Align\\av_hubert\\fairseq-old\\fairseq\\logging\\progress_bar.py", "source_location": "L272"}, {"caller_nid": "logging_progress_bar_simpleprogressbar_log", "callee": "format", "is_member_call": true, "source_file": "C:\\t309\\detectors\\AVH-Align\\av_hubert\\fairseq-old\\fairseq\\logging\\progress_bar.py", "source_location": "L273"}, {"caller_nid": "logging_progress_bar_simpleprogressbar_print", "callee": "info", "is_member_call": true, "source_file": "C:\\t309\\detectors\\AVH-Align\\av_hubert\\fairseq-old\\fairseq\\logging\\progress_bar.py", "source_location": "L282"}, {"caller_nid": "logging_progress_bar_simpleprogressbar_print", "callee": "format", "is_member_call": true, "source_file": "C:\\t309\\detectors\\AVH-Align\\av_hubert\\fairseq-old\\fairseq\\logging\\progress_bar.py", "source_location": "L282"}, {"caller_nid": "logging_progress_bar_tqdmprogressbar_init", "callee": "super", "is_member_call": false, "source_file": "C:\\t309\\detectors\\AVH-Align\\av_hubert\\fairseq-old\\fairseq\\logging\\progress_bar.py", "source_location": "L289"}, {"caller_nid": "logging_progress_bar_tqdmprogressbar_init", "callee": "tqdm", "is_member_call": false, "source_file": "C:\\t309\\detectors\\AVH-Align\\av_hubert\\fairseq-old\\fairseq\\logging\\progress_bar.py", "source_location": "L292"}, {"caller_nid": "logging_progress_bar_tqdmprogressbar_init", "callee": "getEffectiveLevel", "is_member_call": true, "source_file": "C:\\t309\\detectors\\AVH-Align\\av_hubert\\fairseq-old\\fairseq\\logging\\progress_bar.py", "source_location": "L296"}, {"caller_nid": "logging_progress_bar_tqdmprogressbar_iter", "callee": "iter", "is_member_call": false, "source_file": "C:\\t309\\detectors\\AVH-Align\\av_hubert\\fairseq-old\\fairseq\\logging\\progress_bar.py", "source_location": "L300"}, {"caller_nid": "logging_progress_bar_tqdmprogressbar_log", "callee": "set_postfix", "is_member_call": true, "source_file": "C:\\t309\\detectors\\AVH-Align\\av_hubert\\fairseq-old\\fairseq\\logging\\progress_bar.py", "source_location": "L304"}, {"caller_nid": "logging_progress_bar_tqdmprogressbar_print", "callee": "info", "is_member_call": true, "source_file": "C:\\t309\\detectors\\AVH-Align\\av_hubert\\fairseq-old\\fairseq\\logging\\progress_bar.py", "source_location": "L310"}, {"caller_nid": "logging_progress_bar_tqdmprogressbar_print", "callee": "format", "is_member_call": true, "source_file": "C:\\t309\\detectors\\AVH-Align\\av_hubert\\fairseq-old\\fairseq\\logging\\progress_bar.py", "source_location": "L310"}, {"caller_nid": "logging_progress_bar_close_writers", "callee": "values", "is_member_call": true, "source_file": "C:\\t309\\detectors\\AVH-Align\\av_hubert\\fairseq-old\\fairseq\\logging\\progress_bar.py", "source_location": "L324"}, {"caller_nid": "logging_progress_bar_close_writers", "callee": "close", "is_member_call": true, "source_file": "C:\\t309\\detectors\\AVH-Align\\av_hubert\\fairseq-old\\fairseq\\logging\\progress_bar.py", "source_location": "L325"}, {"caller_nid": "logging_progress_bar_tensorboardprogressbarwrapper_init", "callee": "warning", "is_member_call": true, "source_file": "C:\\t309\\detectors\\AVH-Align\\av_hubert\\fairseq-old\\fairseq\\logging\\progress_bar.py", "source_location": "L339"}, {"caller_nid": "logging_progress_bar_tensorboardprogressbarwrapper_writer", "callee": "SummaryWriter", "is_member_call": false, "source_file": "C:\\t309\\detectors\\AVH-Align\\av_hubert\\fairseq-old\\fairseq\\logging\\progress_bar.py", "source_location": "L348"}, {"caller_nid": "logging_progress_bar_tensorboardprogressbarwrapper_writer", "callee": "join", "is_member_call": true, "source_file": "C:\\t309\\detectors\\AVH-Align\\av_hubert\\fairseq-old\\fairseq\\logging\\progress_bar.py", "source_location": "L348"}, {"caller_nid": "logging_progress_bar_tensorboardprogressbarwrapper_writer", "callee": "add_text", "is_member_call": true, "source_file": "C:\\t309\\detectors\\AVH-Align\\av_hubert\\fairseq-old\\fairseq\\logging\\progress_bar.py", "source_location": "L349"}, {"caller_nid": "logging_progress_bar_tensorboardprogressbarwrapper_writer", "callee": "join", "is_member_call": true, "source_file": "C:\\t309\\detectors\\AVH-Align\\av_hubert\\fairseq-old\\fairseq\\logging\\progress_bar.py", "source_location": "L349"}, {"caller_nid": "logging_progress_bar_tensorboardprogressbarwrapper_iter", "callee": "iter", "is_member_call": false, "source_file": "C:\\t309\\detectors\\AVH-Align\\av_hubert\\fairseq-old\\fairseq\\logging\\progress_bar.py", "source_location": "L353"}, {"caller_nid": "logging_progress_bar_tensorboardprogressbarwrapper_log_to_tensorboard", "callee": "keys", "is_member_call": true, "source_file": "C:\\t309\\detectors\\AVH-Align\\av_hubert\\fairseq-old\\fairseq\\logging\\progress_bar.py", "source_location": "L376"}, {"caller_nid": "logging_progress_bar_tensorboardprogressbarwrapper_log_to_tensorboard", "callee": "isinstance", "is_member_call": false, "source_file": "C:\\t309\\detectors\\AVH-Align\\av_hubert\\fairseq-old\\fairseq\\logging\\progress_bar.py", "source_location": "L377"}, {"caller_nid": "logging_progress_bar_tensorboardprogressbarwrapper_log_to_tensorboard", "callee": "add_scalar", "is_member_call": true, "source_file": "C:\\t309\\detectors\\AVH-Align\\av_hubert\\fairseq-old\\fairseq\\logging\\progress_bar.py", "source_location": "L378"}, {"caller_nid": "logging_progress_bar_tensorboardprogressbarwrapper_log_to_tensorboard", "callee": "isinstance", "is_member_call": false, "source_file": "C:\\t309\\detectors\\AVH-Align\\av_hubert\\fairseq-old\\fairseq\\logging\\progress_bar.py", "source_location": "L379"}, {"caller_nid": "logging_progress_bar_tensorboardprogressbarwrapper_log_to_tensorboard", "callee": "add_scalar", "is_member_call": true, "source_file": "C:\\t309\\detectors\\AVH-Align\\av_hubert\\fairseq-old\\fairseq\\logging\\progress_bar.py", "source_location": "L380"}, {"caller_nid": "logging_progress_bar_tensorboardprogressbarwrapper_log_to_tensorboard", "callee": "is_tensor", "is_member_call": true, "source_file": "C:\\t309\\detectors\\AVH-Align\\av_hubert\\fairseq-old\\fairseq\\logging\\progress_bar.py", "source_location": "L381"}, {"caller_nid": "logging_progress_bar_tensorboardprogressbarwrapper_log_to_tensorboard", "callee": "numel", "is_member_call": true, "source_file": "C:\\t309\\detectors\\AVH-Align\\av_hubert\\fairseq-old\\fairseq\\logging\\progress_bar.py", "source_location": "L381"}, {"caller_nid": "logging_progress_bar_tensorboardprogressbarwrapper_log_to_tensorboard", "callee": "add_scalar", "is_member_call": true, "source_file": "C:\\t309\\detectors\\AVH-Align\\av_hubert\\fairseq-old\\fairseq\\logging\\progress_bar.py", "source_location": "L382"}, {"caller_nid": "logging_progress_bar_tensorboardprogressbarwrapper_log_to_tensorboard", "callee": "item", "is_member_call": true, "source_file": "C:\\t309\\detectors\\AVH-Align\\av_hubert\\fairseq-old\\fairseq\\logging\\progress_bar.py", "source_location": "L382"}, {"caller_nid": "logging_progress_bar_tensorboardprogressbarwrapper_log_to_tensorboard", "callee": "flush", "is_member_call": true, "source_file": "C:\\t309\\detectors\\AVH-Align\\av_hubert\\fairseq-old\\fairseq\\logging\\progress_bar.py", "source_location": "L383"}, {"caller_nid": "logging_progress_bar_wandbprogressbarwrapper_init", "callee": "warning", "is_member_call": true, "source_file": "C:\\t309\\detectors\\AVH-Align\\av_hubert\\fairseq-old\\fairseq\\logging\\progress_bar.py", "source_location": "L398"}, {"caller_nid": "logging_progress_bar_wandbprogressbarwrapper_init", "callee": "init", "is_member_call": true, "source_file": "C:\\t309\\detectors\\AVH-Align\\av_hubert\\fairseq-old\\fairseq\\logging\\progress_bar.py", "source_location": "L403"}, {"caller_nid": "logging_progress_bar_wandbprogressbarwrapper_iter", "callee": "iter", "is_member_call": false, "source_file": "C:\\t309\\detectors\\AVH-Align\\av_hubert\\fairseq-old\\fairseq\\logging\\progress_bar.py", "source_location": "L406"}, {"caller_nid": "logging_progress_bar_wandbprogressbarwrapper_update_config", "callee": "update", "is_member_call": true, "source_file": "C:\\t309\\detectors\\AVH-Align\\av_hubert\\fairseq-old\\fairseq\\logging\\progress_bar.py", "source_location": "L421"}, {"caller_nid": "logging_progress_bar_wandbprogressbarwrapper_log_to_wandb", "callee": "keys", "is_member_call": true, "source_file": "C:\\t309\\detectors\\AVH-Align\\av_hubert\\fairseq-old\\fairseq\\logging\\progress_bar.py", "source_location": "L432"}, {"caller_nid": "logging_progress_bar_wandbprogressbarwrapper_log_to_wandb", "callee": "isinstance", "is_member_call": false, "source_file": "C:\\t309\\detectors\\AVH-Align\\av_hubert\\fairseq-old\\fairseq\\logging\\progress_bar.py", "source_location": "L433"}, {"caller_nid": "logging_progress_bar_wandbprogressbarwrapper_log_to_wandb", "callee": "isinstance", "is_member_call": false, "source_file": "C:\\t309\\detectors\\AVH-Align\\av_hubert\\fairseq-old\\fairseq\\logging\\progress_bar.py", "source_location": "L435"}, {"caller_nid": "logging_progress_bar_azuremlprogressbarwrapper_init", "callee": "warning", "is_member_call": true, "source_file": "C:\\t309\\detectors\\AVH-Align\\av_hubert\\fairseq-old\\fairseq\\logging\\progress_bar.py", "source_location": "L451"}, {"caller_nid": "logging_progress_bar_azuremlprogressbarwrapper_init", "callee": "get_context", "is_member_call": true, "source_file": "C:\\t309\\detectors\\AVH-Align\\av_hubert\\fairseq-old\\fairseq\\logging\\progress_bar.py", "source_location": "L453"}, {"caller_nid": "logging_progress_bar_azuremlprogressbarwrapper_exit", "callee": "complete", "is_member_call": true, "source_file": "C:\\t309\\detectors\\AVH-Align\\av_hubert\\fairseq-old\\fairseq\\logging\\progress_bar.py", "source_location": "L457"}, {"caller_nid": "logging_progress_bar_azuremlprogressbarwrapper_iter", "callee": "iter", "is_member_call": false, "source_file": "C:\\t309\\detectors\\AVH-Align\\av_hubert\\fairseq-old\\fairseq\\logging\\progress_bar.py", "source_location": "L461"}, {"caller_nid": "logging_progress_bar_azuremlprogressbarwrapper_log_to_azureml", "callee": "keys", "is_member_call": true, "source_file": "C:\\t309\\detectors\\AVH-Align\\av_hubert\\fairseq-old\\fairseq\\logging\\progress_bar.py", "source_location": "L485"}, {"caller_nid": "logging_progress_bar_azuremlprogressbarwrapper_log_to_azureml", "callee": "isinstance", "is_member_call": false, "source_file": "C:\\t309\\detectors\\AVH-Align\\av_hubert\\fairseq-old\\fairseq\\logging\\progress_bar.py", "source_location": "L487"}, {"caller_nid": "logging_progress_bar_azuremlprogressbarwrapper_log_to_azureml", "callee": "log_row", "is_member_call": true, "source_file": "C:\\t309\\detectors\\AVH-Align\\av_hubert\\fairseq-old\\fairseq\\logging\\progress_bar.py", "source_location": "L488"}, {"caller_nid": "logging_progress_bar_azuremlprogressbarwrapper_log_to_azureml", "callee": "isinstance", "is_member_call": false, "source_file": "C:\\t309\\detectors\\AVH-Align\\av_hubert\\fairseq-old\\fairseq\\logging\\progress_bar.py", "source_location": "L489"}, {"caller_nid": "logging_progress_bar_azuremlprogressbarwrapper_log_to_azureml", "callee": "log_row", "is_member_call": true, "source_file": "C:\\t309\\detectors\\AVH-Align\\av_hubert\\fairseq-old\\fairseq\\logging\\progress_bar.py", "source_location": "L490"}]}